Workbook

Sheet H0系统预排
O1: SIT权限检查（ 外部：1代表权限已配好，反之则为2。 内部：3代表、权限已配好，反之则为4） | U1: 查看当前账号关联的经销商（单个）数据 | AI1: 查看当前登录事业部的所有数据 | AT1: 以事业部维度，查看个人创建或者个人关联经销商数据。特殊，列表看个人创建，单据详情可选全部经销商：折扣政策、战略报备），当菜单包含战略项目字样时，再增加一个或者当前单据的项目经理=当前用户 | AX1: 以事业部维度，查看个人创建或个人关联经销商或当前部门下属所管辖经销商数据 | AZ1: 查看当前登录事业部所有的数据 | CK1: MBO业务
A2: 菜单编码（唯一） | B2: 一级菜单 | C2: 二级菜单 | D2: 三级菜单 | E2: 菜单渠道属性 | F2: 经销商可阅 | G2: 内部可阅/废弃 | H2: 涉及系统 | I2: 生产需复核 | J2: AE_MENUID | K2: 备注 | L2: 原菜单路径1 | M2: 原菜单路径2 | N2: 原菜单路径3 | O2: 配置优先级 | P2: 技术配置 | Q2: 汉得复核 | R2: 箭牌复核sit | S2: 默认菜单按钮权限（针对本表所有角色） | T2: █经销商按钮权限█ | U2: 经销商 主账号 | V2: 法人账号 | W2: 经销商 负责人 | X2: 经销商 采购 | Y2: 经销商 仓管 | Z2: 经销商 财务 | AA2: 经销商工程报备 | AB2: 经销商家装报备 | AC2: 经销商产品专员 | AD2: 出口经销商 | AE2: 电子合同签章 | AF2: 经销商工程核销 | AG2: 经销商家装核销 | AH2: 经销商延期核销 | AI2: 价格查询 | AJ2: 工厂库存查询 | AL2: 库存查询 | AM2: 工程报备专员 | AN2: 家装报备专员 | AO2: 报备查询 | AP2: 工程合同专员 | AQ2: 家装合同专员 | AR2: 运营管理 | AS2: █报备、合同、运营默认按钮权限█ | AT2: 战略工程项目管理 | AU2: 工程项目管理 | AV2: 家装项目管理 | AW2: 区域销售代表 | AX2: 大区管理 | AY2: █项目、区域销售默认权限█ | AZ2: 发货专员 | BA2: 调度专员 | BB2: 计划物流 | BC2: █发货、调度、物流默认权限█ | BD2: 销售财务 | BE2: █销售财务默认权限█ | BF2: 认领核销 | BG2: BI人员查看 | BH2: AE-工程合同及折扣单查看 | BI2: 自营工程签收 | BJ2: 发票作废与取消核销 | BK2: 真实性核销审核 | BL2: 库存查询 | BM2: 库存查询（映射） | BN2: 价格查询 | BO2: 价格查询（导出） | BP2: 产品查询（所有） | BQ2: 产品查询（导出） | BR2: 产品查询 | BS2: 产品维护 | BT2: 产品推广等级维护 | BU2: 产品SM状态变更 | BV2: 售后产品SM状态变更 | BW2: 产品说明书维护 | BX2: 软装经理 | BY2: 软装总监 | BZ2: 合同及订单查询 | CA2: 展示总监（新增） | CB2: 合同档案管理员（新增） | CC2: 展示部人员 | CD2: 样品折扣政策查询 | CE2: 装修报销标准维护 | CF2: 门店档案资料查询（新） | CG2: 单体项目报备导出 | CH2: 家装折扣政策查询 | CI2: 门店装修报表查询 | CJ2: █产品维护权限█ | CK2: 培训师 | CL2: 活动策划师 | CM2: 设计师 | CN2: 培训管理员 | CO2: 活动策划管理员 | CP2: 设计师管理员 | CQ2: 集团合同管理员 | CR2: 问题反馈处理回复 | CS2: 菜单使用频率 | CT2: 最新更新时间（按sj精确到时分秒） | CU2: 更新记录（调整人+调整内容+调整时间）
A3: 1 | B3: 基础资料 | C3: 客户资料 | D3: 经销商档案 | E3: 全渠道 | F3: 是 | G3: 是 | H3: CRM/AE/MBO | J3: 12036281，12036115 | K3: （查询+新建地址） | O3: 3 | P3: 1、3 | T3: 编辑 | U3: √ | W3: √ | X3: √ | Z3: √ | AR3: √ | AW3: √ | AX3: √ | AZ3: √ | BB3: √ | BC3: 编辑 | BD3: √ | BE3: 编辑,导出 | BX3: √ | BY3: √ | BZ3: √ | CC3: √ | CS3: =COUNTIF(U3:CR3,"=√") -> 14
A4: 2 | B4: 基础资料 | C4: 客户资料 | D4: 法人客户档案 | E4: 全渠道 | F4: 法人 | G4: 是 | H4: CRM/AE/MBO | J4: 12036284 | L4: AMCS-基础资料-法人客户档案 | M4: AMCS-基础资料-交易公司 | O4: 3 | P4: 1、3 | U4: 见法人对账 | V4: √ | Z4: √ | AR4: √ | AW4: √ | AX4: √ | AZ4: √ | BB4: √ | BC4: 编辑 | BD4: √ | BE4: 导出 | BX4: √ | CS4: =COUNTIF(U4:CR4,"=√") -> 9
A5: 3 | B5: 基础资料 | C5: 客户资料 | D5: 供应商档案 | E5: 全渠道 | G5: 是 | H5: AE | J5: 12036282，12035823 | O5: 9 | S5: 除导出外不限 | AP5: √ | AQ5: √ | AR5: √ | AS5: 全部数据 | AT5: √ | AU5: √ | AW5: √ | AX5: √ | AY5: 编辑,全部数据 | BD5: √ | BE5: 导出,全部数据 | CS5: =COUNTIF(U5:CR5,"=√") -> 8
A6: 4 | B6: 基础资料 | C6: 客户资料 | D6: 分销商档案 | E6: 全渠道 | F6: 是 | G6: 是 | H6: AE | J6: 12036349 | O6: 3 | P6: 1、3 | S6: 除导出外不限 | T6: 编辑 | U6: √ | W6: √ | Z6: √ | AR6: √ | AS6: 编辑,失效,生效 | AW6: √ | AX6: √ | AY6: 编辑,失效,生效 | BD6: √ | BE6: 导出 | CC6: √ | CS6: =COUNTIF(U6:CR6,"=√") -> 8 | CT6: 46138.449 | CU6: 2026-4-26 10:47:01：莫小丽“新增运营及区域销售可操作失效与恢复生效按钮
A7: 231 | B7: 基础资料 | C7: 订单设置 | D7: 产品线关联设置 | E7: 全渠道 | G7: IT | H7: CRM/AE | J7: 12036136 | O7: 10 | P7: 未开发 | S7: 不限 | CS7: =COUNTIF(U7:CR7,"=√") -> 0
A8: 232 | B8: 基础资料 | C8: 订单设置 | D8: 产品渠道设置 | E8: 全渠道 | G8: IT | H8: CRM/AE | J8: 12036141 | O8: 10 | P8: 3 | S8: 不限 | CS8: =COUNTIF(U8:CR8,"=√") -> 0
A9: 233 | B9: 基础资料 | C9: 订单设置 | D9: 业务渠道设置 | E9: 全渠道 | G9: IT | H9: CRM/AE | J9: 12036145 | O9: 10 | P9: 3 | S9: 不限 | CS9: =COUNTIF(U9:CR9,"=√") -> 0
A10: 234 | B10: 基础资料 | C10: 订单设置 | D10: 产品线维护 | E10: 全渠道 | G10: IT | H10: CRM/AE | J10: 12036146 | O10: 10 | P10: 3 | S10: 不限 | CS10: =COUNTIF(U10:CR10,"=√") -> 0
A11: 235 | B11: 基础资料 | C11: 常规设置 | D11: 行政区域 | E11: 全渠道 | G11: IT | H11: CRM/AE/MBO | J11: 12036290，12036160 | O11: 10 | S11: 不限 | AM11: √ | AN11: √ | AP11: √ | AQ11: √ | AR11: √ | AS11: 全部数据 | AT11: √ | AU11: √ | AV11: √ | AW11: √ | AX11: √ | AY11: 全部数据 | BD11: √ | BE11: 全部数据 | CS11: =COUNTIF(U11:CR11,"=√") -> 11
A12: 236 | B12: 基础资料 | C12: 常规设置 | D12: 事业部设置 | E12: 全渠道 | G12: IT | H12: CRM/AE | J12: 12036287，12036150 | O12: 10 | P12: 无需配置 | S12: 不限 | CS12: =COUNTIF(U12:CR12,"=√") -> 0
A13: 237 | B13: 基础资料 | C13: 常规设置 | D13: 合同类型与销售渠道关联关系设置 | E13: 全渠道 | G13: IT | H13: AE | J13: 12036482 | O13: 10 | S13: 不限 | CS13: =COUNTIF(U13:CR13,"=√") -> 0
A14: 238 | B14: 基础资料 | C14: 常规设置 | D14: 项目进度定义 | E14: 工程 | G14: IT | H14: AE | J14: 12035897 | O14: 10 | S14: 不限 | CS14: =COUNTIF(U14:CR14,"=√") -> 0
A15: 5 | B15: 基础资料 | C15: 常规设置 | D15: 行政销售区域对照列表 | E15: 全渠道 | G15: 是 | H15: AE | J15: 12036463 | O15: 9 | S15: 不限 | AM15: √ | AP15: √ | AR15: √ | AS15: 编辑,导出 | BD15: √ | CS15: =COUNTIF(U15:CR15,"=√") -> 4
A16: 6 | B16: 基础资料 | C16: 常规设置 | D16: 单据审批人对照表 | E16: 全渠道 | H16: AE | J16: 12036464 | O16: 9 | S16: 不限 | AM16: √ | AP16: √ | AR16: √ | AS16: 编辑,导出 | BD16: √ | CS16: =COUNTIF(U16:CR16,"=√") -> 4
A17: 240 | B17: 基础资料 | C17: 常规设置 | D17: 数据权限设置 | E17: 全渠道 | G17: IT | H17: AE | J17: 12036163 | O17: 10 | S17: 不限 | CS17: =COUNTIF(U17:CR17,"=√") -> 0
A18: 241 | B18: 基础资料 | C18: 常规设置 | D18: 经销商配置 | E18: 全渠道 | G18: IT | H18: AE | J18: 12036389 | O18: 10 | S18: 不限 | CS18: =COUNTIF(U18:CR18,"=√") -> 0
A19: 289 | B19: 基础资料 | C19: 常规设置 | D19: AE和CRM事业部对应关系表配置 | E19: 全渠道 | G19: IT | H19: CRM/AE | O19: 10 | S19: 不限 | CS19: =COUNTIF(U19:CR19,"=√") -> 0
A20: 7 | B20: 基础资料 | C20: 常规设置 | D20: 节假日维护（无） | E20: 全渠道 | G20: 是 | H20: AE | J20: 12036492 | O20: 9 | S20: 不限 | AM20: √ | AR20: √ | AS20: 编辑,导出,全部数据 | BD20: √ | BE20: 全部数据 | CS20: =COUNTIF(U20:CR20,"=√") -> 3
A21: 8 | B21: 产品中心 | C21: 产品资料 | D21: 产品列表 | E21: 全渠道 | F21: 是 | G21: 是 | H21: CRM/AE | J21: 12036297 | O21: 3 | P21: 1、3 | T21: 导出 | U21: √ | W21: √ | X21: √ | Z21: √ | AC21: √ | AM21: √ | AN21: √ | AP21: √ | AQ21: √ | AR21: √ | AT21: √ | AU21: √ | AV21: √ | AW21: √ | AX21: √ | AY21: 关联事业部的全部 | AZ21: √ | BA21: √ | BB21: √ | BC21: 导出 | BD21: √ | BP21: √ | BQ21: √ | BR21: √ | BS21: √ | BU21: √ | BV21: √ | CS21: =COUNTIF(U21:CR21,"=√") -> 25 | CT21: 2026年4月22日21:15:52 | CU21: 区肇蓉+新增角色“产品查询（所有）、产品查询”+2026.4.22”
A22: 9 | B22: 产品中心 | C22: 产品资料 | D22: 产品变更列表 | E22: 全渠道 | G22: 是 | H22: CRM/AE | K22: 包含上下架、推广资料、图册与附件、关联产品 | O22: 9 | P22: 3 | BA22: √ | BB22: √ | BS22: √ | CS22: =COUNTIF(U22:CR22,"=√") -> 3
A23: 10 | B23: 产品中心 | C23: 产品资料 | D23: 产品推广等级字段要求配置 | E23: 全渠道 | G23: 是 | H23: CRM/AE | O23: 9 | P23: 3 | BT23: √ | CS23: =COUNTIF(U23:CR23,"=√") -> 1
A24: 11 | B24: 产品中心 | C24: 产品资料 | D24: 产品推广等级维护 | E24: 全渠道 | G24: 是 | H24: CRM/AE | O24: 9 | P24: 3 | BT24: √ | CJ24: 编辑,导出 | CS24: =COUNTIF(U24:CR24,"=√") -> 1
A25: 12 | B25: 产品中心 | C25: 产品资料 | D25: 产品图册维护（废弃原AE功能） | E25: 全渠道 | G25: 是 | H25: CRM/AE | J25: 12036299 | L25: AE产品图册上传 | M25: AE产品图册 | O25: 9 | BS25: √ | CS25: =COUNTIF(U25:CR25,"=√") -> 1
A26: 13 | B26: 产品中心 | C26: 产品资料 | D26: 产品SM状态变更申请 | E26: 全渠道 | G26: 是 | H26: AE | J26: 12036305 | O26: 4 | S26: 不限 | BU26: √ | BV26: √ | CS26: =COUNTIF(U26:CR26,"=√") -> 2
A27: 14 | B27: 产品中心 | C27: 说明书 | D27: 产品说明书 | E27: 全渠道 | G27: 是 | H27: AE | I27: 内 | J27: 12036368 | O27: 4 | P27: 3 | S27: 不限 | BW27: √ | CS27: =COUNTIF(U27:CR27,"=√") -> 1
A28: 15 | B28: 产品中心 | C28: 说明书 | D28: 说明书分类 | E28: 全渠道 | G28: 是 | H28: AE | J28: 12036367 | O28: 9 | S28: 除导出外不限 | BW28: √ | CS28: =COUNTIF(U28:CR28,"=√") -> 1
A29: 16 | B29: 产品中心 | C29: 说明书 | D29: 说明书查阅数据 | E29: 全渠道 | G29: 是 | H29: AE | J29: 12036369 | O29: 9 | P29: 无需配置 | S29: 除导出外不限 | BW29: √ | CS29: =COUNTIF(U29:CR29,"=√") -> 1
A30: 17 | B30: 产品中心 | C30: 说明书 | D30: 说明书关联产品 | E30: 全渠道 | G30: 是 | H30: AE | J30: 12036373 | O30: 9 | S30: 除导出外不限 | BW30: √ | CS30: =COUNTIF(U30:CR30,"=√") -> 1
A31: 242 | B31: 产品中心 | C31: 产品设置 | D31: (未来) | E31: 全渠道 | G31: IT | H31: CRM | L31: 经销商维护自选可售产品清单 | O31: 10 | CS31: =COUNTIF(U31:CR31,"=√") -> 0
A32: 18 | B32: 产品中心 | C32: 价目表 | D32: 价目表查询 | E32: 全渠道 | F32: 是 | G32: 是 | H32: CRM/AE | J32: 12036465 | K32: 12036466 | L32: 价目表 | O32: 3 | P32: 1、3 | U32: √ | W32: √ | X32: √ | Z32: √ | AI32: √ | AR32: √ | AT32: √ | AU32: √ | AV32: √ | AW32: √ | AX32: √ | AY32: 关联事业部的全部数据 | AZ32: √ | BA32: √ | BB32: √ | BD32: √ | BE32: 导出 | BN32: √ | BO32: √ | BZ32: √ | CS32: =COUNTIF(U32:CR32,"=√") -> 18 | CT32: 2026年4月25日10:55:52 | CU32: 区肇蓉+新增角色“价格查询、价格查询（导出）”+2026.4.25”
A33: 19 | B33: 产品中心 | C33: 库存 | D33: 库存查询 | E33: 全渠道 | F33: 是 | G33: 是 | H33: CRM/AE | J33: 12036152 | K33: 经销商/内部， | L33: 库存查询 | O33: 3 | P33: 1、3 | U33: √ | W33: √ | X33: √ | Y33: √ | Z33: √ | AJ33: √ | AL33: √ | AR33: √ | AT33: √ | AU33: √ | AV33: √ | AW33: √ | AX33: √ | AY33: 关联事业部的全部数据 | AZ33: √ | BA33: √ | BB33: √ | BD33: √ | BL33: √ | BM33: √ | CS33: =COUNTIF(U33:CR33,"=√") -> 19 | CT33: 2026年4月22日21:15:52 | CU33: 区肇蓉+新增角色“库存查询（映射）+2026.4.22”
A34: 20 | B34: 产品中心 | C34: 库存 | D34: 库存查询 | E34: 全渠道 | G34: 是，未来 | H34: CRM | K34: (内部-未来) | O34: 11 | AU34: √ | AV34: √ | AW34: √ | AX34: √ | AY34: 关联事业部的全部数据 | CS34: =COUNTIF(U34:CR34,"=√") -> 4
A35: 21 | B35: 产品中心 | C35: 库存 | D35: 事业部库存查询 | E35: 全渠道 | F35: 是 | G35: 是 | H35: CRM | K35: （经销商)责任制 | L35: 事业部库存查询 | P35: 1 | U35: √ | W35: √ | X35: √ | Y35: √ | Z35: √ | CS35: =COUNTIF(U35:CR35,"=√") -> 5 | CT35: 2026年4月18日17:32:52 | CU35: 区肇蓉，拿掉软装总监、软装经理关于“事业部库存查询”勾选，内部用户不涉及权限
A36: 22 | B36: 门店管理 | C36: 门店档案 | D36: 新建门店申请 | E36: 全渠道 | F36: 是 | G36: 是 | H36: AE | J36: 12036309 | O36: 3 | P36: 1、3 | S36: 除导出外不限 | T36: 编辑 | U36: √ | W36: √ | Z36: √ | AD36: √ | AR36: √ | AW36: √ | AX36: √ | AY36: 编辑 | BD36: √ | BE36: 导出 | CC36: √ | CS36: =COUNTIF(U36:CR36,"=√") -> 9
A37: 23 | B37: 门店管理 | C37: 门店档案 | D37: 门店档案 | E37: 全渠道 | F37: 是 | G37: 是 | H37: AE | J37: 12036311 | O37: 3 | P37: 1、3 | U37: √ | W37: √ | Z37: √ | AD37: √ | AR37: √ | AS37: 导出 | AW37: √ | AX37: √ | AY37: 导出 | BD37: √ | BE37: 导出 | BG37: √ | CC37: √ | CF37: √导出 | CS37: =COUNTIF(U37:CR37,"=√") -> 10
A38: 24 | B38: 门店管理 | C38: 门店档案 | D38: 门店变更申请 | E38: 全渠道 | F38: 是 | G38: 是 | H38: AE | J38: 12036312 | O38: 3 | P38: 1、3 | S38: 除导出外不限 | T38: 编辑 | U38: √ | W38: √ | Z38: √ | AD38: √ | AR38: √ | AW38: √ | AX38: √ | AY38: 编辑 | BD38: √ | BE38: 导出 | CC38: √ | CF38: √导出 | CS38: =COUNTIF(U38:CR38,"=√") -> 9
A39: 25 | B39: 门店管理 | C39: 门店设置 | D39: 门店照片设置 | E39: 全渠道 | H39: AE | J39: 12036313 | O39: 9 | P39: 3 | AR39: √ | AS39: 编辑,导出 | AW39: √ | AX39: √ | AY39: 关联事业部的全部数据 | BD39: √ | BE39: 导出 | CC39: √ | CS39: =COUNTIF(U39:CR39,"=√") -> 5
A40: 26 | B40: 门店管理 | C40: 门店设置 | D40: 门店验收信息设置 | E40: 全渠道 | H40: AE | J40: 12036421 | O40: 9 | AR40: √ | AS40: 编辑,导出 | AW40: √ | AX40: √ | AY40: 关联事业部的全部数据 | BD40: √ | BE40: 导出 | CS40: =COUNTIF(U40:CR40,"=√") -> 4
A41: 27 | B41: 门店管理 | C41: 门店设置 | D41: 门店装修标准 | E41: 全渠道 | G41: 是 | H41: AE | J41: 12036422 | O41: 6 | P41: 3 | AR41: √ | AS41: 编辑,导出 | AW41: √ | AX41: √ | AY41: 关联事业部的全部数据 | BD41: √ | BE41: 导出 | CC41: √ | CE41: √ | CS41: =COUNTIF(U41:CR41,"=√") -> 6
A42: 28 | B42: 门店管理 | C42: 门店档案 | D42: 门头展板报销标准 | E42: 全渠道 | G42: 是 | H42: AE | J42: 12036508 | O42: 6 | AR42: √ | AS42: 编辑,导出 | AW42: √ | AX42: √ | AY42: 关联事业部的全部数据 | BD42: √ | BE42: 导出 | CC42: √ | CE42: √ | CS42: =COUNTIF(U42:CR42,"=√") -> 6
A43: 29 | B43: 门店管理 | C43: 门店设置 | D43: 经销商额度外限额 | E43: 全渠道 | H43: AE | J43: 12036509 | O43: 9 | AR43: √ | AS43: 编辑,导出 | AY43: 关联事业部的全部数据 | BD43: √ | BE43: 导出 | CS43: =COUNTIF(U43:CR43,"=√") -> 2 | CT43: 2026年4月14日20:08:52 | CU43: 林辅深：区域经理不要给权限，此单据没有审批流程，菜单权限控制在运营&财务手上
A44: 30 | B44: 门店管理 | C44: 门店装修 | D44: 门店装修申请与进度更新 | E44: 全渠道 | F44: 是 | G44: 是 | H44: AE | I44: 是 | J44: 12036417 | O44: 2 | P44: 1、3 | S44: 查看流程,打印 | T44: 编辑,作废,重新生成 | U44: √ | W44: √ | Z44: √ | AR44: √ | AW44: √ | AX44: √ | BD44: √ | BE44: 导出 | BG44: √ | BX44: √ | BY44: √ | CA44: √ | CC44: √ | CS44: =COUNTIF(U44:CR44,"=√") -> 12
A45: 31 | B45: 门店管理 | C45: 门店装修 | D45: 门店验收与报销单 | E45: 全渠道 | F45: 是 | G45: 是 | H45: AE | I45: 是 | J45: 12036454 | O45: 2 | P45: 1，3 | S45: 查看流程,打印 | T45: 编辑,作废,添加软装订单,移除软装订单 | U45: √ | W45: √ | Z45: √ | AR45: √ | AW45: √ | AX45: √ | AY45: 盖章申请 | BD45: √ | BE45: 导出 | BG45: √ | BX45: √ | BY45: √ | CA45: √ | CC45: √ | CQ45: √ | CS45: =COUNTIF(U45:CR45,"=√") -> 13
A46: 32 | B46: 门店管理 | C46: 门店装修 | D46: 门店装修额内兑现 | E46: 全渠道 | F46: 是 | G46: 是 | H46: AE | J46: 12036434 | O46: 3 | P46: 1、3 | U46: √ | W46: √ | Z46: √ | AR46: √ | AW46: √ | AX46: √ | BD46: √ | BE46: 导出 | BG46: √ | CS46: =COUNTIF(U46:CR46,"=√") -> 8
A47: 33 | B47: 门店管理 | C47: 门店装修 | D47: 额度内兑现批量复核 | E47: 全渠道 | G47: 财务 | H47: AE | J47: 12036441 | O47: 4 | S47: 不限 | BD47: √ | BE47: 导出 | BG47: √ | CS47: =COUNTIF(U47:CR47,"=√") -> 2
A48: 34 | B48: 门店管理 | C48: 门店装修 | D48: 门店装修额度外兑现 | E48: 全渠道 | F48: 是 | G48: 是 | H48: AE | J48: 12036419 | O48: 2 | P48: 1、3 | S48: 查看流程 | T48: 编辑 | U48: √ | W48: √ | Z48: √ | AR48: √ | AS48: 编辑,导出 | AW48: √ | AX48: √ | BD48: √ | BE48: 导出 | BG48: √ | CQ48: √ | CS48: =COUNTIF(U48:CR48,"=√") -> 9 | CT48: 2026年4月29日10:31:54
A49: 35 | B49: 门店管理 | C49: 门店装修 | D49: 门店装修申请变更 | E49: 全渠道 | F49: 是 | G49: 是 | H49: AE | J49: 12036440 | O49: 2 | P49: 1、3 | S49: 查看流程,打印 | T49: 编辑,作废 | U49: √ | W49: √ | Z49: √ | AR49: √ | AW49: √ | AX49: √ | BD49: √ | BE49: 导出 | BG49: √ | CS49: =COUNTIF(U49:CR49,"=√") -> 8
A50: 36 | B50: 门店管理 | C50: 门店装修 | D50: 门店装修申请关闭 | E50: 全渠道 | F50: 是 | G50: 是 | H50: AE | J50: 12036420 | O50: 5 | P50: 1、3 | S50: 查看流程 | T50: 编辑 | U50: √ | W50: √ | Z50: √ | AR50: √ | AW50: √ | AX50: √ | AY50: 编辑 | BD50: √ | BE50: 导出 | BG50: √ | CS50: =COUNTIF(U50:CR50,"=√") -> 8
A51: 37 | B51: 门店管理 | C51: 门店装修 | D51: 门头展板报销申请单 | E51: 全渠道 | F51: 是 | G51: 是 | H51: AE | I51: 是 | J51: 12036510 | O51: 2 | P51: 1、3 | S51: 查看流程,打印 | T51: 编辑 | U51: √ | W51: √ | Z51: √ | AR51: √ | AS51: 导出 | AW51: √ | AX51: √ | AY51: 编辑,发起签署 | BD51: √ | BE51: 导出 | CA51: √ | CI51: √ | CQ51: √ | CS51: =COUNTIF(U51:CR51,"=√") -> 10
A52: 38 | B52: 门店管理 | C52: 门店装修 | D52: 门头展板兑现 | E52: 全渠道 | F52: 是 | G52: 是 | H52: AE | I52: 是 | J52: 12036511 | O52: 2 | P52: 1、3 | S52: 查看流程,打印 | T52: 编辑 | U52: √ | W52: √ | Z52: √ | AR52: √ | AS52: 导出 | AW52: √ | AX52: √ | AY52: 编辑 | BD52: √ | BE52: 导出 | CA52: √ | CS52: =COUNTIF(U52:CR52,"=√") -> 8
A53: 39 | B53: 门店管理 | C53: 广告投放 | D53: 广告投放申请 | E53: 全渠道 | F53: 是 | G53: 是 | H53: AE | J53: 12036351 | K53: 额度内外业务合并 | L53: 广告投放申请 | M53: 额度外广告投放申请 | O53: 2 | P53: 1、3 | S53: 除导出外不限 | T53: 编辑 | U53: √ | W53: √ | Z53: √ | AR53: √ | AS53: 编辑,导出 | AW53: √ | AX53: √ | AY53: 编辑 | BD53: √ | BE53: 导出 | BG53: √ | CA53: √ | CC53: √ | CS53: =COUNTIF(U53:CR53,"=√") -> 10
A54: 40 | B54: 门店管理 | C54: 广告投放 | D54: 广告费报销 | E54: 全渠道 | F54: 是 | G54: 是 | H54: AE | J54: 12036352 | K54: 额度内外业务合并 | L54: 广告费报销 | M54: 额度外广告费报销 | O54: 2 | P54: 1、3 | S54: 除导出外不限 | T54: 编辑 | U54: √ | W54: √ | Z54: √ | AR54: √ | AS54: 编辑,导出 | AW54: √ | AX54: √ | AY54: 编辑 | BD54: √ | BE54: 导出 | BG54: √ | CA54: √ | CC54: √ | CS54: =COUNTIF(U54:CR54,"=√") -> 10
A55: 41 | B55: 门店管理 | C55: 广告投放 | D55: 广告报销发票兑现 | E55: 全渠道 | F55: 是 | G55: 是 | H55: AE | J55: 12036360 | K55: 额度内外业务合并 | L55: 广告报销兑现 | M55: 额度外广告报销兑现 | O55: 2 | P55: 1、3 | S55: 除导出外不限,打印 | T55: 编辑,打印 | U55: √ | W55: √ | Z55: √ | AR55: √ | AS55: 编辑,导出 | AW55: √ | AX55: √ | AY55: 编辑,发起签署 | BD55: √ | BE55: 导出 | BG55: √ | CA55: √ | CQ55: √ | CS55: =COUNTIF(U55:CR55,"=√") -> 10 | CT55: 46138.45 | CU55: （1）2026-4-26 10:48:05“莫小丽区域销售新增可操作”发起签署“按钮
A56: 42 | B56: 门店管理 | C56: 样品管理 | D56: 待定 | F56: 待定 | G56: 是，未来 | H56: AE/MBO | L56: 门店上样登记 | O56: 11 | CS56: =COUNTIF(U56:CR56,"=√") -> 0
A57: 43 | B57: 门店管理 | C57: 样品管理 | D57: 待定 | F57: 待定 | G57: 是，未来 | H57: AE/MBO | L57: 门店样品处理 | O57: 11 | CS57: =COUNTIF(U57:CR57,"=√") -> 0
A58: 44 | B58: 门店管理 | C58: 装修报表 | D58: 门店装修额外兑现报表 | E58: 全渠道 | G58: 是 | H58: AE | J58: 12036453 | L58: 门店装修额外兑现报表 | O58: 9 | AR58: √ | BD58: √ | BE58: 导出 | CI58: √ | CS58: =COUNTIF(U58:CR58,"=√") -> 3
A59: 46 | B59: 门店管理 | C59: 装修报表 | D59: 门店装修申请与进度更新报表 | E59: 全渠道 | G59: 是 | H59: AE | J59: 12036455 | L59: 门店装修申请与进度更新报表 | O59: 9 | AR59: √ | BD59: √ | BE59: 导出 | CI59: √ | CS59: =COUNTIF(U59:CR59,"=√") -> 3
A60: 296 | B60: 门店管理 | C60: 门店装修 | D60: 门店验收与报销单报表 | E60: 全渠道 | G60: 是 | H60: AE | O60: 9 | P60: 1，3 | AR60: √ | BD60: √ | BE60: 导出 | CI60: √ | CS60: =COUNTIF(U60:CR60,"=√") -> 3 | CT60: 46131.939 | CU60: 莫小丽：漏菜单，补充权限
A61: 47 | B61: 门店管理 | C61: 装修报表 | D61: 额度内兑现统计报表 | E61: 全渠道 | G61: 是 | H61: AE | J61: 12036456 | L61: 额度内兑现统计报表 | O61: 9 | BD61: √ | BE61: 导出 | CS61: =COUNTIF(U61:CR61,"=√") -> 1
A62: 48 | B62: 门店管理 | C62: 装修报表 | D62: 店面额度内兑现余额表 | E62: 全渠道 | G62: 是 | H62: AE | J62: 12036488 | L62: 店面额度内兑现余额表 | O62: 9 | BD62: √ | BE62: 导出 | CS62: =COUNTIF(U62:CR62,"=√") -> 1
A63: 49 | B63: 门店管理 | C63: 装修报表 | D63: 额度外台账（无） | E63: 全渠道 | G63: 是 | H63: AE | J63: 12036435 | L63: 额度外台账 | O63: 9 | AR63: √ | BD63: √ | BE63: 导出 | CS63: =COUNTIF(U63:CR63,"=√") -> 2
A64: 50 | B64: 门店管理 | C64: 装修报表 | D64: 额度内台账（无） | E64: 全渠道 | G64: 是 | H64: AE | J64: 12036437 | L64: 额度内台账 | O64: 9 | AR64: √ | BD64: √ | BE64: 导出 | CS64: =COUNTIF(U64:CR64,"=√") -> 2
A65: 51 | B65: 门店管理 | C65: 装修报表 | D65: 兑现汇总 | E65: 全渠道 | G65: 是 | H65: AE | J65: 12036436 | L65: 兑现汇总 | O65: 9 | AR65: √ | BD65: √ | BE65: 导出 | CS65: =COUNTIF(U65:CR65,"=√") -> 2
A66: 52 | B66: 门店管理 | C66: 门店报表 | D66: 门店查询与分布（无） | E66: 全渠道 | G66: 是 | H66: AE | J66: 12036354 | L66: 门店查询与分布 | O66: 9 | AR66: √ | AW66: √ | AX66: √ | BD66: √ | BE66: 导出 | CC66: √ | CS66: =COUNTIF(U66:CR66,"=√") -> 5
A67: 53 | B67: 门店管理 | C67: 门店报表 | D67: 门店统计分析 | E67: 全渠道 | G67: 是 | H67: AE | J67: 12036338 | L67: 门店统计分析 | O67: 9 | AR67: √ | AW67: √ | AX67: √ | BD67: √ | BE67: 导出 | CS67: =COUNTIF(U67:CR67,"=√") -> 4
A68: 54 | B68: 门店管理 | C68: 门店报表 | D68: 门店区域分布 | E68: 全渠道 | G68: 是 | H68: AE | J68: 12036401 | L68: 门店区域分布 | O68: 9 | AR68: √ | AW68: √ | AX68: √ | BD68: √ | BE68: 导出 | CS68: =COUNTIF(U68:CR68,"=√") -> 4
A69: 55 | B69: 门店管理 | C69: 门店报表 | D69: 户外广告分布 | E69: 全渠道 | G69: 是 | H69: AE | J69: 12036341 | L69: 户外广告分布 | O69: 9 | AR69: √ | AW69: √ | AX69: √ | BD69: √ | BE69: 导出 | CC69: √ | CS69: =COUNTIF(U69:CR69,"=√") -> 5
A70: 56 | B70: 门店管理 | C70: 门店报表 | D70: 门店分析（无） | E70: 全渠道 | G70: 是 | H70: AE | J70: 12036365 | L70: 门店分析 | O70: 9 | AR70: √ | AW70: √ | AX70: √ | BD70: √ | BE70: 导出 | CS70: =COUNTIF(U70:CR70,"=√") -> 4
A71: 57 | B71: 工程管理 | C71: 项目商机 | D71: 单体项目报备 | E71: 工程 | F71: 是 | G71: 是 | H71: AE | I71: 是 | J71: 12035833 | O71: 1 | P71: 1、3 | R71: 1 | T71: 编辑,申诉 | U71: √ | AA71: √ | AM71: √,更新标准地址及信息,查重 | AO71: √,查重 | BG71: √ | CG71: √导出 | CS71: =COUNTIF(U71:CR71,"=√") -> 3
A72: 58 | B72: 工程管理 | C72: 项目商机 | D72: 项目进度更新 | E72: 工程 | F72: 是 | G72: 是 | H72: AE | J72: 12035834 | O72: 4 | P72: 1、3 | R72: 1 | T72: 编辑 | U72: √ | AA72: √ | AM72: √ | CS72: =COUNTIF(U72:CR72,"=√") -> 3
A73: 59 | B73: 工程管理 | C73: 项目商机 | D73: 战略项目报备 | E73: 工程 | G73: 是 | H73: AE | J73: 12035908 | O73: 2 | P73: 1、3 | AM73: √ | AO73: √ | AT73: √ | AX73: √ | AY73: 编辑,查看流程,二次报备,个人创建的数据,项目经理为他 | BG73: √ | CS73: =COUNTIF(U73:CR73,"=√") -> 5 | CT73: 46138.451 | CU73: （1）2026-4-26 10:49:24莫小丽：战略工程管理新增可二次报备按钮，可查看项目经理为他的数据权限
A74: 60 | B74: 工程管理 | C74: 项目商机 | D74: 工程项目档案 | E74: 工程 | F74: 是 | G74: 是 | H74: AE | J74: 12036099 | O74: 9 | AM74: √ | BG74: √ | CS74: =COUNTIF(U74:CR74,"=√") -> 2
A75: 61 | B75: 工程管理 | C75: 项目商机 | D75: 报备解冻申请 | E75: 工程 | F75: 是 | G75: 是 | H75: AE | I75: 是 | J75: 12036165 | O75: 3 | P75: 3 | R75: 2 | S75: 除导出外不限 | T75: 编辑 | U75: √ | AA75: √ | AM75: √ | BG75: √ | CS75: =COUNTIF(U75:CR75,"=√") -> 4
A76: 62 | B76: 工程管理 | C76: 项目商机 | D76: 报备生/失效申请 | E76: 工程 | G76: 是 | H76: AE | J76: 12036168 | K76: 12036195 | L76: 单体项目报备失效申请 | M76: 单体项目报备生效申请 | O76: 6 | AM76: √ | AS76: 编辑 | BG76: √ | CS76: =COUNTIF(U76:CR76,"=√") -> 2 | CT76: 46151.653 | CU76: 1、2026-5-9 15:40:58取消经销商可查看权限
A77: 63 | B77: 工程管理 | C77: 项目商机 | D77: 战略报备变更 | E77: 工程 | G77: 是 | H77: AE | J77: 12036178 | O77: 4 | AM77: √ | AT77: √ | AX77: √ | AY77: 编辑,查看流程,个人创建的数据,项目经理为他 | CS77: =COUNTIF(U77:CR77,"=√") -> 3 | CT77: 46138.451 | CU77: （1）2026-4-26 10:49:24莫小丽：战略工程管理新增可二次报备按钮，可查看项目经理为他的数据权限
A78: 64 | B78: 工程管理 | C78: 项目商机 | D78: 战略经理变更 | E78: 工程 | G78: 是 | H78: AE | J78: 12036375 | O78: 5 | S78: 导入,导出 | AM78: √ | AS78: 编辑 | CS78: =COUNTIF(U78:CR78,"=√") -> 1 | CT78: 46145.675 | CU78: 2026-5-3 16:11:52莫小丽，增加默认导出权限
A79: 65 | B79: 工程管理 | C79: 项目商机 | D79: 工程项目结案 | E79: 工程 | F79: 是 | G79: 是 | H79: AE | J79: 12035846 | O79: 4 | P79: 1、3 | R79: 2 | T79: 编辑 | U79: √ | AA79: √ | AM79: √ | CS79: =COUNTIF(U79:CR79,"=√") -> 3
A80: 66 | B80: 工程管理 | C80: 项目合同 | D80: 经销商工程合同 | E80: 工程 | F80: 是 | G80: 是 | H80: AE | I80: 是 | J80: 12035844 | O80: 1 | P80: 1、3 | R80: 1 | S80: 增补合同 | T80: 编辑 | U80: √ | AA80: √ | AP80: √ | AS80: 失效,导出 | AT80: √ | AU80: √ | AX80: √ | BA80: √ | BD80: √ | BE80: 导出 | BG80: √ | BH80: √ | BZ80: √ | CS80: =COUNTIF(U80:CR80,"=√") -> 11 | CT80: 46136.397 | CU80: 莫小丽：增加角色：AE-工程合同及折扣单查看，可查看工程合同，工程折扣单
A81: 67 | B81: 工程管理 | C81: 项目合同 | D81: 自营工程合同 | E81: 工程 | F81: 是 | G81: 是 | H81: AE | I81: 是 | J81: 12035907 | O81: 1 | P81: 1、3 | R81: 1 | S81: 增补合同 | T81: 编辑 | U81: √ | AA81: √ | AP81: √ | AS81: 失效,导出 | AT81: √ | AU81: √ | AX81: √ | BA81: √ | BD81: √ | BE81: 导出 | BG81: √ | BH81: √ | BZ81: √ | CS81: =COUNTIF(U81:CR81,"=√") -> 11 | CT81: 46136.397 | CU81: 莫小丽：增加角色：AE-工程合同及折扣单查看，可查看工程合同，工程折扣单；20260709：经销商工程报备增加自营工程合同申请权限
A82: 68 | B82: 工程管理 | C82: 项目交付 | D82: 工程合同产品变更 | E82: 工程 | F82: 是 | G82: 是 | H82: AE | I82: 是 | J82: 12036157 | O82: 1 | P82: 1、3 | R82: 1 | S82: 删除 | T82: 编辑,删除 | U82: √ | AA82: √ | AP82: √ | AS82: 导出 | AT82: √ | AU82: √ | AX82: √ | BD82: √ | BE82: 导出 | CS82: =COUNTIF(U82:CR82,"=√") -> 7
A83: 69 | B83: 工程管理 | C83: 项目交付 | D83: 工程折扣延期 | E83: 工程 | F83: 是 | G83: 是 | H83: AE | I83: 是 | J83: 12036166 | O83: 1 | P83: 1、3 | R83: 1 | S83: 删除 | T83: 编辑,删除 | U83: √ | AA83: √ | AP83: √ | AS83: 导出 | AT83: √ | AU83: √ | AX83: √ | BD83: √ | BE83: 导出 | CS83: =COUNTIF(U83:CR83,"=√") -> 7
A84: 70 | B84: 工程管理 | C84: 合同与折扣 | D84: 工程折扣单 | E84: 工程 | F84: 是 | G84: 是 | H84: AE | I84: 是 | J84: 12035849 | O84: 1 | P84: 1、3 | R84: 2 | S84: 除导出外不限 | T84: 编辑,合同产品变更,生成订单 | U84: √ | AA84: √ | AP84: √ | AS84: 导出 | AT84: √ | AU84: √ | AX84: √ | BA84: √ | BD84: √ | BE84: 导出 | BH84: √ | BZ84: √ | CS84: =COUNTIF(U84:CR84,"=√") -> 10 | CT84: 46138.445 | CU84: （1）2026-4-24：莫小丽：增加角色：AE-工程合同及折扣单查看，可查看工程合同，工程折扣单 （2）2026-4-26 10:41:19增加经销商可操作生成订单、合同产品变更按钮（此按钮需满足条件才会出现）
A85: 71 | B85: 工程管理 | C85: 合同与折扣 | D85: 项目合同变更 | E85: 工程 | G85: 是 | H85: AE | J85: 12035845 | O85: 5 | P85: 3 | S85: 除导出外不限 | AP85: √ | BD85: √ | BE85: 导出 | CS85: =COUNTIF(U85:CR85,"=√") -> 2
A86: 72 | B86: 工程管理 | C86: 项目交付 | D86: 工程折扣政策申请 | E86: 工程 | G86: 是 | H86: AE | J86: 12036490 | O86: 5 | S86: 除导出外不限 | AR86: √ | AS86: 编辑 | AU86: √ | AX86: √ | AZ86: √ | BD86: √ | BE86: 导出 | BG86: √ | CS86: =COUNTIF(U86:CR86,"=√") -> 6
A87: 73 | B87: 工程管理 | C87: 项目交付 | D87: 工程折扣政策失效 | E87: 工程 | G87: 是 | H87: AE | J87: 12036491 | O87: 8 | S87: 除导出外不限 | AR87: √ | AS87: 编辑,导出 | BD87: √ | BE87: 导出 | CS87: =COUNTIF(U87:CR87,"=√") -> 2
A88: 74 | B88: 工程管理 | C88: 项目交付 | D88: 工程要货订单 | E88: 工程 | F88: 是 | G88: 是 | H88: AE | I88: 是 | J88: 12035851 | O88: 1 | P88: 1、3 | R88: 1 | S88: 同步地址信息,查看定金与库存,申请不扣定金,打印 | T88: 编辑,修改地址 | U88: √ | X88: √ | Z88: √ | AD88: √ | AP88: √ | AS88: 导出 | AT88: √ | AU88: √ | AX88: √ | AZ88: √ | BB88: √ | BD88: √ | BE88: 导出 | BZ88: √ | CS88: =COUNTIF(U88:CR88,"=√") -> 12
A89: 75 | B89: 工程管理 | C89: 合同与折扣 | D89: 工程自营签收 | E89: 工程 | F89: 是 | G89: 是 | H89: AE | I89: 内 | J89: 12035854 | O89: 1 | P89: 1、3 | R89: 2 | S89: 编辑 | T89: 编辑 | U89: √ | Z89: √ | AP89: √ | AR89: √ | AT89: √ | AU89: √ | AX89: √ | AY89: 导出 | BD89: √ | BE89: 导出 | BI89: √ | CS89: =COUNTIF(U89:CR89,"=√") -> 9 | CT89: 46128.417 | CU89: 莫小丽：默认权限增加“编辑”（2026-4-16 10:00:18） 运营管理角色新增自营工程签收权限，数据权限为当前事业部数据
A90: 76 | B90: 工程管理 | C90: 项目交付 | D90: 订单紧急要货/紧急要货订单 | E90: 工程 | F90: 是 | G90: 是 | H90: AE | J90: 12036177 | O90: 5 | P90: 1、3 | R90: 功能权限有问题，先去掉权限 | S90: 除导出外不限 | T90: 编辑 | U90: √ | X90: √ | Z90: √ | AP90: √ | AU90: √ | AX90: √ | AZ90: √ | BB90: √ | BD90: √ | BE90: 导出 | CS90: =COUNTIF(U90:CR90,"=√") -> 9
A91: 77 | B91: 工程管理 | C91: 项目交付 | D91: 提货时间变更 | E91: 工程 | G91: 是 | H91: AE | J91: 12036189 | O91: 9 | Z91: √ | AZ91: √ | BB91: √ | BC91: 编辑 | BD91: √ | BE91: 导出 | CS91: =COUNTIF(U91:CR91,"=√") -> 4
A92: 78 | B92: 工程管理 | C92: 项目交付 | D92: 有效延期申请 | E92: 工程 | F92: 是 | G92: 是 | H92: AE | J92: 12036190 | O92: 6 | P92: 1，3 | S92: 除导出外不限 | T92: 编辑 | U92: √ | X92: √ | Z92: √ | AU92: √ | AX92: √ | AZ92: √ | BB92: √ | BC92: 编辑 | BD92: √ | BE92: 导出 | CS92: =COUNTIF(U92:CR92,"=√") -> 8
A93: 79 | B93: 工程管理 | C93: 项目交付 | D93: 紧急要货插单 | E93: 工程 | G93: 是 | H93: AE | J93: 12036191 | O93: 9 | S93: 除导出外不限 | Z93: √ | AZ93: √ | BB93: √ | BC93: 编辑 | BD93: √ | BE93: 导出 | CS93: =COUNTIF(U93:CR93,"=√") -> 4
A94: 80 | B94: 工程管理 | C94: 项目交付 | D94: 工程要货订单报表 | E94: 工程 | F94: 是 | G94: 是 | H94: AE | J94: 12036171 | O94: 5 | P94: 1，3 | S94: 除导出外不限 | U94: √ | Z94: √ | AP94: √ | AT94: √ | AU94: √ | AX94: √ | BD94: √ | BE94: 导出 | CS94: =COUNTIF(U94:CR94,"=√") -> 7
A95: 81 | B95: 工程管理 | C95: 项目交付 | D95: 折扣单报表 | E95: 工程 | F95: 是 | G95: 是 | H95: AE | J95: 12036173 | O95: 5 | P95: 1、3 | S95: 除导出外不限 | U95: √ | Z95: √ | AP95: √ | AT95: √ | AU95: √ | AX95: √ | BD95: √ | BE95: 导出 | BZ95: √ | CS95: =COUNTIF(U95:CR95,"=√") -> 8
A96: 82 | B96: 工程管理 | C96: 项目交付 | D96: 紧急要货报表 | E96: 工程 | F96: 是 | G96: 是 | H96: AE | J96: 12036196 | O96: 10 | S96: 除导出外不限 | AZ96: √ | BB96: √ | BD96: √ | BE96: 导出 | CS96: =COUNTIF(U96:CR96,"=√") -> 3
A97: 83 | B97: 工程管理 | C97: 项目交付 | D97: 提货时间变更表 | E97: 工程 | G97: 是 | H97: AE | J97: 12036197 | O97: 9 | S97: 除导出外不限 | AZ97: √ | BB97: √ | BD97: √ | BE97: 导出 | CS97: =COUNTIF(U97:CR97,"=√") -> 3
A98: 84 | B98: 工程管理 | C98: 项目交付 | D98: 插单记录表 | E98: 工程 | G98: 是 | H98: AE | J98: 12036198 | O98: 9 | S98: 除导出外不限 | AZ98: √ | BB98: √ | BD98: √ | BE98: 导出 | CS98: =COUNTIF(U98:CR98,"=√") -> 3
A99: 85 | B99: 工程管理 | C99: 服务费 | D99: 工程服务费报销 | E99: 工程 | F99: 是 | G99: 是 | H99: AE | I99: 是 | J99: 12036461 | O99: 2 | P99: 1、3 | S99: 除导出外不限 | T99: 编辑 | U99: √ | Z99: √ | AM99: √ | AP99: √ | BD99: √ | BE99: 导出 | CS99: =COUNTIF(U99:CR99,"=√") -> 5
A100: 86 | B100: 工程管理 | C100: 服务费 | D100: 工程服务费兑现 | E100: 工程 | F100: 是 | G100: 是 | H100: AE | I100: 是 | J100: 12036462 | O100: 1 | P100: 1、3 | S100: 除导出外不限 | T100: 编辑 | U100: √ | Z100: √ | AM100: √ | AP100: √ | BD100: √ | BE100: 导出 | CS100: =COUNTIF(U100:CR100,"=√") -> 5
...

Sheet 新系统菜单样式
A1: 左侧平铺菜单样式（系统默认值）
A4: 左侧呼出菜单样式（用户可选1，仅影响个人账号样式）
A7: 顶部悬浮菜单样式（用户可选2，仅影响个人账号样式）
A10: 顶部及左侧固定菜单样式（用户可选3，仅影响个人账号样式）

Sheet 批量操作日志
A1: 更新时间 | B1: 更新内容
A2: 46138.446 | B2: 角色=大区管理“，可查看菜单调整为取“战略项目管理、工程项目管理、家装项目管理”菜单的合集

Sheet 权限下拉列表
B1: √ | G1: 按钮名称 | H1: 按钮类型
B2: 编辑 | G2: 详情页-编辑按钮 | H2: 编辑
B3: 查看流程 | G3: 详情页单据行-增加行按钮 | H3: 编辑
B4: 删除 | G4: 详情页单据行-增加子行按钮 | H4: 编辑
B5: 作废 | G5: 详情页单据行-删除行按钮 | H5: 删除
B6: 失效 | G6: 详情页-保存按钮 | H6: 保存
B7: 生效 | G7: 详情页-生效按钮 | H7: 生效
B8: 导入 | G8: 详情页-失效按钮 | H8: 失效
B9: 导出 | G9: 详情页-创建按钮 | H9: 编辑
B10: 申诉 | G10: 详情页单据行-删除按钮 | H10: 删除
B11: 更新标准地址及信息 | G11: 详情页-取消编辑按钮 | H11: 编辑
B12: 查重 | G12: 详情页-新建按钮 | H12: 编辑
... B31: 合同产品变更 | G31: 详情-打印按钮 | H31: 打印
B32: 生成订单
G33: 导出按钮 | H33: 导出
B34: 打印 | G34: 导入按钮 | H34: 导入
B35: 关联事业部的全部数据 | G35: 详情页单据行-新增按钮 | H35: 编辑
B36: 全部数据 | G36: 详情页-刷新按钮 | H36: 不限
B37: 个人创建的数据 | G37: 详情页单据行-引用政策产品 | H37: 编辑
B38: 个人管辖的经销商数据 | G38: 详情页-试算折扣率按钮 | H38: 编辑
B39: 项目经理为他 | G39: 列表页行-合同增补按钮 | H39: 增补合同
G40: 列表页行-失效按钮 | H40: 失效
G41: 列表页行-编辑按钮 | H41: 编辑
G42: 详情页-获取零售折扣底限按钮 | H42: 编辑
G43: 详情页-获取零售折扣按钮 | H43: 编辑
G44: 详情页-提交按钮 | H44: 编辑
G45: 合同增补 | H45: 增补合同
G46: 新建 | H46: 编辑
G47: 删除 | H47: 删除
G48: 查看 | H48: 不限
G49: 取消编辑按钮 | H49: 编辑
G50: 新建按钮 | H50: 编辑
G51: 删除按钮 | H51: 删除
... G71: 详情页-刷新数据按钮 | H71: 不限

Sheet 一级菜单
A1: 一级菜单 | B1: 二级序号 | C1: 菜单编码 | F1: 二级菜单 | G1: 二级序号 | H1: 三级菜单 | I1: 三级序号
A2: 基础资料 | B2: 1 | C2: =B2&A2 -> 1基础资料 | F2: 客户资料 | G2: 1 | H2: 经销商档案 | I2: 1
A3: 产品中心 | B3: 2 | C3: =B3&A3 -> 2产品中心 | F3: 订单设置 | G3: 2 | H3: 法人客户档案 | I3: 2
A4: 门店管理 | B4: 3 | C4: =B4&A4 -> 3门店管理 | F4: 常规设置 | G4: 3 | H4: 供应商档案 | I4: 3
A5: 工程管理 | B5: 4 | C5: =B5&A5 -> 4工程管理 | F5: 产品资料 | G5: 4 | H5: 分销商档案 | I5: 4
A6: 家装管理 | B6: 5 | C6: =B6&A6 -> 5家装管理 | F6: 说明书 | G6: 5 | H6: 产品线关联设置 | I6: 5
A7: 折扣政策 | B7: 6 | C7: =B7&A7 -> 6折扣政策 | F7: 产品设置 | G7: 6 | H7: 产品渠道设置 | I7: 6
A8: 采购订单 | B8: 7 | C8: =B8&A8 -> 7采购订单 | F8: 价目表 | G8: 7 | H8: 业务渠道设置 | I8: 7
A9: 经销商库存 | B9: 8 | C9: =B9&A9 -> 8经销商库存 | F9: 库存 | G9: 8 | H9: 产品线维护 | I9: 8
A10: 点将管理 | B10: 9 | C10: =B10&A10 -> 9点将管理 | F10: 门店档案 | G10: 9 | H10: 行政区域 | I10: 9
A11: 经销合同管理 | B11: 10 | C11: =B11&A11 -> 10经销合同管理 | F11: 门店设置 | G11: 10 | H11: 事业部设置 | I11: 10
A12: 电子合同管理 | B12: 11 | C12: =B12&A12 -> 11电子合同管理 | F12: 门店装修 | G12: 11 | H12: 合同类型与销售渠道关联关系设置 | I12: 11
A13: 财务管理 | B13: 12 | C13: =B13&A13 -> 12财务管理 | F13: 广告投放 | G13: 12 | H13: 项目进度定义 | I13: 12
... A20: 子账号管理 | B20: 19 | C20: =B20&A20 -> 19子账号管理 | F20: 服务费 | G20: 19 | H20: 产品信息变更申请 | I20: 19
F21: 真实性核销 | G21: 20 | H21: 产品推广等级字段要求配置 | I21: 20
F22: 报表中心 | G22: 21 | H22: 产品推广等级维护 | I22: 21
F23: 家装商机 | G23: 22 | H23: 产品图册维护 | I23: 22
F24: 家装合同 | G24: 23 | H24: 产品SM状态变更申请 | I24: 23
F25: 家装交付 | G25: 24 | H25: 产品说明书 | I25: 24
F26: 样品及长库龄折扣政策申请 | G26: 25 | H26: 说明书分类 | I26: 25
F27: 样品及长库龄折扣政策失效 | G27: 26 | H27: 说明书查阅数据 | I27: 26
F28: 折扣政策申请 | G28: 27 | H28: 说明书关联产品 | I28: 27
F29: 折扣政策失效 | G29: 28 | H29: 价目表查询 | I29: 28
F30: 折扣政策明细查询 | G30: 29 | H30: 库存查询 | I30: 29
F31: 订单查询 | G31: 30 | H31: 事业部库存查询 | I31: 30
F32: 出库单查询 | G32: 31 | H32: 新建门店申请 | I32: 31
... F56: 调整单 | G56: 55 | H56: 店面额度内兑现余额表 | I56: 55
G57: 56 | H57: 额度外台账 | I57: 56
F58: 问题反馈 | G58: 57 | H58: 额度内台账 | I58: 57
F59: 问题回复 | G59: 58 | H59: 兑现汇总 | I59: 58
F60: AE重复或合并的菜单 | G60: 59 | H60: 门店查询与分布 | I60: 59
G61: 60 | H61: 门店统计分析 | I61: 60
G62: 61 | H62: 门店区域分布 | I62: 61
G63: 62 | H63: 户外广告分布 | I63: 62
G64: 63 | H64: 门店分析 | I64: 63
G65: 64 | H65: 单体项目报备 | I65: 64
G66: 65 | H66: 项目进度更新 | I66: 65
G67: 66 | H67: 战略项目报备 | I67: 66
G68: 67 | H68: 工程项目档案 | I68: 67
G69: 68 | H69: 报备解冻申请 | I69: 68
G70: 69 | H70: 报备失效/生效申请 | I70: 69
G71: 70 | H71: 战略报备变更 | I71: 70
G72: 71 | H72: 战略经理变更 | I72: 71
... G219: 218 | H219: 销售提价兑现 | I219: 218
G220: 219 | I220: 219
G221: 220 | I221: 220
G222: 221 | I222: 221
G223: 222 | I223: 222
G224: 223 | I224: 223
G225: 224 | I225: 224
G226: 225 | I226: 225
G227: 226 | I227: 226
G228: 227 | I228: 227

Sheet Sheet8
A1: 一级菜单 | B1: 一级菜单序号 | C1: 二级菜单 | D1: 一级菜单编码 | E1: 一级菜单描述 | F1: 二级菜单序号 | G1: 二级菜单编码 | H1: 二级菜单 | K1: 内部可阅 | L1: 34
A2: 基础资料 | B2: =VLOOKUP(A2,'一级菜单'!A:C,3,0) -> 1基础资料 | C2: 客户资料 | D2: =B2&"_"&F2 -> 1基础资料_1 | E2: =A2&"/"&C2 -> 基础资料/客户资料 | F2: =VLOOKUP(C2,'一级菜单'!F:G,2,0) -> 1 | G2: =D2&"_"&I2 -> 1基础资料_1_1 | H2: 经销商档案 | I2: =VLOOKUP(H2,'一级菜单'!H:I,2,0) -> 1 | J2: =B2&"_"&F2&"_"&I2 -> 1基础资料_1_1 | K2: 是 | L2: CRM,AE,MBO
A3: 基础资料 | B3: =VLOOKUP(A3,'一级菜单'!A:C,3,0) -> 1基础资料 | C3: 客户资料 | D3: =B3&"_"&F3 -> 1基础资料_1 | E3: =A3&"/"&C3 -> 基础资料/客户资料 | F3: =VLOOKUP(C3,'一级菜单'!F:G,2,0) -> 1 | G3: =D3&"_"&I3 -> 1基础资料_1_2 | H3: 法人客户档案 | I3: =VLOOKUP(H3,'一级菜单'!H:I,2,0) -> 2 | J3: =B3&"_"&F3&"_"&I3 -> 1基础资料_1_2 | K3: 是 | L3: CRM,AE,MBO
A4: 基础资料 | B4: =VLOOKUP(A4,'一级菜单'!A:C,3,0) -> 1基础资料 | C4: 客户资料 | D4: =B4&"_"&F4 -> 1基础资料_1 | E4: =A4&"/"&C4 -> 基础资料/客户资料 | F4: =VLOOKUP(C4,'一级菜单'!F:G,2,0) -> 1 | G4: =D4&"_"&I4 -> 1基础资料_1_3 | H4: 供应商档案 | I4: =VLOOKUP(H4,'一级菜单'!H:I,2,0) -> 3 | J4: =B4&"_"&F4&"_"&I4 -> 1基础资料_1_3 | K4: 是 | L4: AE
A5: 基础资料 | B5: =VLOOKUP(A5,'一级菜单'!A:C,3,0) -> 1基础资料 | C5: 客户资料 | D5: =B5&"_"&F5 -> 1基础资料_1 | E5: =A5&"/"&C5 -> 基础资料/客户资料 | F5: =VLOOKUP(C5,'一级菜单'!F:G,2,0) -> 1 | G5: =D5&"_"&I5 -> 1基础资料_1_4 | H5: 分销商档案 | I5: =VLOOKUP(H5,'一级菜单'!H:I,2,0) -> 4 | J5: =B5&"_"&F5&"_"&I5 -> 1基础资料_1_4 | K5: 是 | L5: AE
A6: 基础资料 | B6: =VLOOKUP(A6,'一级菜单'!A:C,3,0) -> 1基础资料 | C6: 订单设置 | D6: =B6&"_"&F6 -> 1基础资料_2 | E6: =A6&"/"&C6 -> 基础资料/订单设置 | F6: =VLOOKUP(C6,'一级菜单'!F:G,2,0) -> 2 | G6: =D6&"_"&I6 -> 1基础资料_2_5 | H6: 产品线关联设置 | I6: =VLOOKUP(H6,'一级菜单'!H:I,2,0) -> 5 | J6: =B6&"_"&F6&"_"&I6 -> 1基础资料_2_5 | K6: IT | L6: CRM,AE
A7: 基础资料 | B7: =VLOOKUP(A7,'一级菜单'!A:C,3,0) -> 1基础资料 | C7: 订单设置 | D7: =B7&"_"&F7 -> 1基础资料_2 | E7: =A7&"/"&C7 -> 基础资料/订单设置 | F7: =VLOOKUP(C7,'一级菜单'!F:G,2,0) -> 2 | G7: =D7&"_"&I7 -> 1基础资料_2_6 | H7: 产品渠道设置 | I7: =VLOOKUP(H7,'一级菜单'!H:I,2,0) -> 6 | J7: =B7&"_"&F7&"_"&I7 -> 1基础资料_2_6 | K7: IT | L7: CRM,AE
A8: 基础资料 | B8: =VLOOKUP(A8,'一级菜单'!A:C,3,0) -> 1基础资料 | C8: 订单设置 | D8: =B8&"_"&F8 -> 1基础资料_2 | E8: =A8&"/"&C8 -> 基础资料/订单设置 | F8: =VLOOKUP(C8,'一级菜单'!F:G,2,0) -> 2 | G8: =D8&"_"&I8 -> 1基础资料_2_7 | H8: 业务渠道设置 | I8: =VLOOKUP(H8,'一级菜单'!H:I,2,0) -> 7 | J8: =B8&"_"&F8&"_"&I8 -> 1基础资料_2_7 | K8: IT | L8: CRM,AE
A9: 基础资料 | B9: =VLOOKUP(A9,'一级菜单'!A:C,3,0) -> 1基础资料 | C9: 订单设置 | D9: =B9&"_"&F9 -> 1基础资料_2 | E9: =A9&"/"&C9 -> 基础资料/订单设置 | F9: =VLOOKUP(C9,'一级菜单'!F:G,2,0) -> 2 | G9: =D9&"_"&I9 -> 1基础资料_2_8 | H9: 产品线维护 | I9: =VLOOKUP(H9,'一级菜单'!H:I,2,0) -> 8 | J9: =B9&"_"&F9&"_"&I9 -> 1基础资料_2_8 | K9: IT | L9: CRM,AE
A10: 基础资料 | B10: =VLOOKUP(A10,'一级菜单'!A:C,3,0) -> 1基础资料 | C10: 常规设置 | D10: =B10&"_"&F10 -> 1基础资料_3 | E10: =A10&"/"&C10 -> 基础资料/常规设置 | F10: =VLOOKUP(C10,'一级菜单'!F:G,2,0) -> 3 | G10: =D10&"_"&I10 -> 1基础资料_3_9 | H10: 行政区域 | I10: =VLOOKUP(H10,'一级菜单'!H:I,2,0) -> 9 | J10: =B10&"_"&F10&"_"&I10 -> 1基础资料_3_9 | K10: IT | L10: CRM,AE,MBO
A11: 基础资料 | B11: =VLOOKUP(A11,'一级菜单'!A:C,3,0) -> 1基础资料 | C11: 常规设置 | D11: =B11&"_"&F11 -> 1基础资料_3 | E11: =A11&"/"&C11 -> 基础资料/常规设置 | F11: =VLOOKUP(C11,'一级菜单'!F:G,2,0) -> 3 | G11: =D11&"_"&I11 -> 1基础资料_3_10 | H11: 事业部设置 | I11: =VLOOKUP(H11,'一级菜单'!H:I,2,0) -> 10 | J11: =B11&"_"&F11&"_"&I11 -> 1基础资料_3_10 | K11: IT | L11: CRM,AE
A12: 基础资料 | B12: =VLOOKUP(A12,'一级菜单'!A:C,3,0) -> 1基础资料 | C12: 常规设置 | D12: =B12&"_"&F12 -> 1基础资料_3 | E12: =A12&"/"&C12 -> 基础资料/常规设置 | F12: =VLOOKUP(C12,'一级菜单'!F:G,2,0) -> 3 | G12: =D12&"_"&I12 -> 1基础资料_3_11 | H12: 合同类型与销售渠道关联关系设置 | I12: =VLOOKUP(H12,'一级菜单'!H:I,2,0) -> 11 | J12: =B12&"_"&F12&"_"&I12 -> 1基础资料_3_11 | K12: IT | L12: AE
A13: 基础资料 | B13: =VLOOKUP(A13,'一级菜单'!A:C,3,0) -> 1基础资料 | C13: 常规设置 | D13: =B13&"_"&F13 -> 1基础资料_3 | E13: =A13&"/"&C13 -> 基础资料/常规设置 | F13: =VLOOKUP(C13,'一级菜单'!F:G,2,0) -> 3 | G13: =D13&"_"&I13 -> 1基础资料_3_12 | H13: 项目进度定义 | I13: =VLOOKUP(H13,'一级菜单'!H:I,2,0) -> 12 | J13: =B13&"_"&F13&"_"&I13 -> 1基础资料_3_12 | K13: IT | L13: AE
A14: 基础资料 | B14: =VLOOKUP(A14,'一级菜单'!A:C,3,0) -> 1基础资料 | C14: 常规设置 | D14: =B14&"_"&F14 -> 1基础资料_3 | E14: =A14&"/"&C14 -> 基础资料/常规设置 | F14: =VLOOKUP(C14,'一级菜单'!F:G,2,0) -> 3 | G14: =D14&"_"&I14 -> 1基础资料_3_13 | H14: 行政销售区域对照列表 | I14: =VLOOKUP(H14,'一级菜单'!H:I,2,0) -> 13 | J14: =B14&"_"&F14&"_"&I14 -> 1基础资料_3_13 | K14: 是 | L14: AE
A15: 基础资料 | B15: =VLOOKUP(A15,'一级菜单'!A:C,3,0) -> 1基础资料 | C15: 常规设置 | D15: =B15&"_"&F15 -> 1基础资料_3 | E15: =A15&"/"&C15 -> 基础资料/常规设置 | F15: =VLOOKUP(C15,'一级菜单'!F:G,2,0) -> 3 | G15: =D15&"_"&I15 -> 1基础资料_3_14 | H15: 单据审批人对照列表 | I15: =VLOOKUP(H15,'一级菜单'!H:I,2,0) -> 14 | J15: =B15&"_"&F15&"_"&I15 -> 1基础资料_3_14 | L15: AE
A16: 基础资料 | B16: =VLOOKUP(A16,'一级菜单'!A:C,3,0) -> 1基础资料 | C16: 常规设置 | D16: =B16&"_"&F16 -> 1基础资料_3 | E16: =A16&"/"&C16 -> 基础资料/常规设置 | F16: =VLOOKUP(C16,'一级菜单'!F:G,2,0) -> 3 | G16: =D16&"_"&I16 -> 1基础资料_3_10 | H16: 事业部设置 | I16: =VLOOKUP(H16,'一级菜单'!H:I,2,0) -> 10 | J16: =B16&"_"&F16&"_"&I16 -> 1基础资料_3_10 | K16: IT | L16: AE
A17: 基础资料 | B17: =VLOOKUP(A17,'一级菜单'!A:C,3,0) -> 1基础资料 | C17: 常规设置 | D17: =B17&"_"&F17 -> 1基础资料_3 | E17: =A17&"/"&C17 -> 基础资料/常规设置 | F17: =VLOOKUP(C17,'一级菜单'!F:G,2,0) -> 3 | G17: =D17&"_"&I17 -> 1基础资料_3_15 | H17: 数据权限设置 | I17: =VLOOKUP(H17,'一级菜单'!H:I,2,0) -> 15 | J17: =B17&"_"&F17&"_"&I17 -> 1基础资料_3_15 | K17: IT | L17: AE
A18: 基础资料 | B18: =VLOOKUP(A18,'一级菜单'!A:C,3,0) -> 1基础资料 | C18: 常规设置 | D18: =B18&"_"&F18 -> 1基础资料_3 | E18: =A18&"/"&C18 -> 基础资料/常规设置 | F18: =VLOOKUP(C18,'一级菜单'!F:G,2,0) -> 3 | G18: =D18&"_"&I18 -> 1基础资料_3_16 | H18: 经销商配置 | I18: =VLOOKUP(H18,'一级菜单'!H:I,2,0) -> 16 | J18: =B18&"_"&F18&"_"&I18 -> 1基础资料_3_16 | K18: IT | L18: AE
A19: 基础资料 | B19: =VLOOKUP(A19,'一级菜单'!A:C,3,0) -> 1基础资料 | C19: 常规设置 | D19: =B19&"_"&F19 -> 1基础资料_3 | E19: =A19&"/"&C19 -> 基础资料/常规设置 | F19: =VLOOKUP(C19,'一级菜单'!F:G,2,0) -> 3 | G19: =D19&"_"&I19 -> 1基础资料_3_17 | H19: 节假日维护 | I19: =VLOOKUP(H19,'一级菜单'!H:I,2,0) -> 17 | J19: =B19&"_"&F19&"_"&I19 -> 1基础资料_3_17 | K19: 是 | L19: AE
A20: 产品中心 | B20: =VLOOKUP(A20,'一级菜单'!A:C,3,0) -> 2产品中心 | C20: 产品资料 | D20: =B20&"_"&F20 -> 2产品中心_4 | E20: =A20&"/"&C20 -> 产品中心/产品资料 | F20: =VLOOKUP(C20,'一级菜单'!F:G,2,0) -> 4 | G20: =D20&"_"&I20 -> 2产品中心_4_18 | H20: 产品资料 | I20: =VLOOKUP(H20,'一级菜单'!H:I,2,0) -> 18 | J20: =B20&"_"&F20&"_"&I20 -> 2产品中心_4_18 | K20: 是 | L20: CRM,AE
A21: 产品中心 | B21: =VLOOKUP(A21,'一级菜单'!A:C,3,0) -> 2产品中心 | C21: 产品资料 | D21: =B21&"_"&F21 -> 2产品中心_4 | E21: =A21&"/"&C21 -> 产品中心/产品资料 | F21: =VLOOKUP(C21,'一级菜单'!F:G,2,0) -> 4 | G21: =D21&"_"&I21 -> 2产品中心_4_19 | H21: 产品信息变更申请 | I21: =VLOOKUP(H21,'一级菜单'!H:I,2,0) -> 19 | J21: =B21&"_"&F21&"_"&I21 -> 2产品中心_4_19 | K21: 是 | L21: CRM,AE
A22: 产品中心 | B22: =VLOOKUP(A22,'一级菜单'!A:C,3,0) -> 2产品中心 | C22: 产品资料 | D22: =B22&"_"&F22 -> 2产品中心_4 | E22: =A22&"/"&C22 -> 产品中心/产品资料 | F22: =VLOOKUP(C22,'一级菜单'!F:G,2,0) -> 4 | G22: =D22&"_"&I22 -> 2产品中心_4_20 | H22: 产品推广等级字段要求配置 | I22: =VLOOKUP(H22,'一级菜单'!H:I,2,0) -> 20 | J22: =B22&"_"&F22&"_"&I22 -> 2产品中心_4_20 | K22: 是 | L22: CRM,AE
A23: 产品中心 | B23: =VLOOKUP(A23,'一级菜单'!A:C,3,0) -> 2产品中心 | C23: 产品资料 | D23: =B23&"_"&F23 -> 2产品中心_4 | E23: =A23&"/"&C23 -> 产品中心/产品资料 | F23: =VLOOKUP(C23,'一级菜单'!F:G,2,0) -> 4 | G23: =D23&"_"&I23 -> 2产品中心_4_21 | H23: 产品推广等级维护 | I23: =VLOOKUP(H23,'一级菜单'!H:I,2,0) -> 21 | J23: =B23&"_"&F23&"_"&I23 -> 2产品中心_4_21 | K23: 是 | L23: CRM,AE
A24: 产品中心 | B24: =VLOOKUP(A24,'一级菜单'!A:C,3,0) -> 2产品中心 | C24: 产品资料 | D24: =B24&"_"&F24 -> 2产品中心_4 | E24: =A24&"/"&C24 -> 产品中心/产品资料 | F24: =VLOOKUP(C24,'一级菜单'!F:G,2,0) -> 4 | G24: =D24&"_"&I24 -> 2产品中心_4_22 | H24: 产品图册维护 | I24: =VLOOKUP(H24,'一级菜单'!H:I,2,0) -> 22 | J24: =B24&"_"&F24&"_"&I24 -> 2产品中心_4_22 | K24: 是 | L24: CRM,AE
A25: 产品中心 | B25: =VLOOKUP(A25,'一级菜单'!A:C,3,0) -> 2产品中心 | C25: 产品资料 | D25: =B25&"_"&F25 -> 2产品中心_4 | E25: =A25&"/"&C25 -> 产品中心/产品资料 | F25: =VLOOKUP(C25,'一级菜单'!F:G,2,0) -> 4 | G25: =D25&"_"&I25 -> 2产品中心_4_23 | H25: 产品SM状态变更申请 | I25: =VLOOKUP(H25,'一级菜单'!H:I,2,0) -> 23 | J25: =B25&"_"&F25&"_"&I25 -> 2产品中心_4_23 | K25: 是 | L25: AE
A26: 产品中心 | B26: =VLOOKUP(A26,'一级菜单'!A:C,3,0) -> 2产品中心 | C26: 说明书 | D26: =B26&"_"&F26 -> 2产品中心_5 | E26: =A26&"/"&C26 -> 产品中心/说明书 | F26: =VLOOKUP(C26,'一级菜单'!F:G,2,0) -> 5 | G26: =D26&"_"&I26 -> 2产品中心_5_24 | H26: 产品说明书 | I26: =VLOOKUP(H26,'一级菜单'!H:I,2,0) -> 24 | J26: =B26&"_"&F26&"_"&I26 -> 2产品中心_5_24 | K26: 是 | L26: AE
A27: 产品中心 | B27: =VLOOKUP(A27,'一级菜单'!A:C,3,0) -> 2产品中心 | C27: 说明书 | D27: =B27&"_"&F27 -> 2产品中心_5 | E27: =A27&"/"&C27 -> 产品中心/说明书 | F27: =VLOOKUP(C27,'一级菜单'!F:G,2,0) -> 5 | G27: =D27&"_"&I27 -> 2产品中心_5_25 | H27: 说明书分类 | I27: =VLOOKUP(H27,'一级菜单'!H:I,2,0) -> 25 | J27: =B27&"_"&F27&"_"&I27 -> 2产品中心_5_25 | K27: 是 | L27: AE
... A37: 门店管理 | B37: =VLOOKUP(A37,'一级菜单'!A:C,3,0) -> 3门店管理 | C37: 门店档案 | D37: =B37&"_"&F37 -> 3门店管理_9 | E37: =A37&"/"&C37 -> 门店管理/门店档案 | F37: =VLOOKUP(C37,'一级菜单'!F:G,2,0) -> 9 | G37: =D37&"_"&I37 -> 3门店管理_9_33 | H37: 门店变更申请 | I37: =VLOOKUP(H37,'一级菜单'!H:I,2,0) -> 33 | J37: =B37&"_"&F37&"_"&I37 -> 3门店管理_9_33 | K37: 是 | L37: AE
A38: 门店管理 | B38: =VLOOKUP(A38,'一级菜单'!A:C,3,0) -> 3门店管理 | C38: 门店设置 | D38: =B38&"_"&F38 -> 3门店管理_10 | E38: =A38&"/"&C38 -> 门店管理/门店设置 | F38: =VLOOKUP(C38,'一级菜单'!F:G,2,0) -> 10 | G38: =D38&"_"&I38 -> 3门店管理_10_34 | H38: 门店照片设置 | I38: =VLOOKUP(H38,'一级菜单'!H:I,2,0) -> 34 | J38: =B38&"_"&F38&"_"&I38 -> 3门店管理_10_34 | L38: AE
A39: 门店管理 | B39: =VLOOKUP(A39,'一级菜单'!A:C,3,0) -> 3门店管理 | C39: 门店设置 | D39: =B39&"_"&F39 -> 3门店管理_10 | E39: =A39&"/"&C39 -> 门店管理/门店设置 | F39: =VLOOKUP(C39,'一级菜单'!F:G,2,0) -> 10 | G39: =D39&"_"&I39 -> 3门店管理_10_35 | H39: 门店验收信息设置 | I39: =VLOOKUP(H39,'一级菜单'!H:I,2,0) -> 35 | J39: =B39&"_"&F39&"_"&I39 -> 3门店管理_10_35 | L39: AE
A40: 门店管理 | B40: =VLOOKUP(A40,'一级菜单'!A:C,3,0) -> 3门店管理 | C40: 门店设置 | D40: =B40&"_"&F40 -> 3门店管理_10 | E40: =A40&"/"&C40 -> 门店管理/门店设置 | F40: =VLOOKUP(C40,'一级菜单'!F:G,2,0) -> 10 | G40: =D40&"_"&I40 -> 3门店管理_10_36 | H40: 门店装修标准(新) | I40: =VLOOKUP(H40,'一级菜单'!H:I,2,0) -> 36 | J40: =B40&"_"&F40&"_"&I40 -> 3门店管理_10_36 | K40: 是 | L40: AE
A41: 门店管理 | B41: =VLOOKUP(A41,'一级菜单'!A:C,3,0) -> 3门店管理 | C41: 门店设置 | D41: =B41&"_"&F41 -> 3门店管理_10 | E41: =A41&"/"&C41 -> 门店管理/门店设置 | F41: =VLOOKUP(C41,'一级菜单'!F:G,2,0) -> 10 | G41: =D41&"_"&I41 -> 3门店管理_10_37 | H41: 门头展板报销标准-新 | I41: =VLOOKUP(H41,'一级菜单'!H:I,2,0) -> 37 | J41: =B41&"_"&F41&"_"&I41 -> 3门店管理_10_37 | K41: 是 | L41: AE
A42: 门店管理 | B42: =VLOOKUP(A42,'一级菜单'!A:C,3,0) -> 3门店管理 | C42: 门店设置 | D42: =B42&"_"&F42 -> 3门店管理_10 | E42: =A42&"/"&C42 -> 门店管理/门店设置 | F42: =VLOOKUP(C42,'一级菜单'!F:G,2,0) -> 10 | G42: =D42&"_"&I42 -> 3门店管理_10_38 | H42: 经销商额度外限额 | I42: =VLOOKUP(H42,'一级菜单'!H:I,2,0) -> 38 | J42: =B42&"_"&F42&"_"&I42 -> 3门店管理_10_38 | L42: AE
A43: 门店管理 | B43: =VLOOKUP(A43,'一级菜单'!A:C,3,0) -> 3门店管理 | C43: 门店装修 | D43: =B43&"_"&F43 -> 3门店管理_11 | E43: =A43&"/"&C43 -> 门店管理/门店装修 | F43: =VLOOKUP(C43,'一级菜单'!F:G,2,0) -> 11 | G43: =D43&"_"&I43 -> 3门店管理_11_39 | H43: 门店装修申请与进度更新 | I43: =VLOOKUP(H43,'一级菜单'!H:I,2,0) -> 39 | J43: =B43&"_"&F43&"_"&I43 -> 3门店管理_11_39 | K43: 是 | L43: AE
A44: 门店管理 | B44: =VLOOKUP(A44,'一级菜单'!A:C,3,0) -> 3门店管理 | C44: 门店装修 | D44: =B44&"_"&F44 -> 3门店管理_11 | E44: =A44&"/"&C44 -> 门店管理/门店装修 | F44: =VLOOKUP(C44,'一级菜单'!F:G,2,0) -> 11 | G44: =D44&"_"&I44 -> 3门店管理_11_40 | H44: 门店验收与报销单 | I44: =VLOOKUP(H44,'一级菜单'!H:I,2,0) -> 40 | J44: =B44&"_"&F44&"_"&I44 -> 3门店管理_11_40 | K44: 是 | L44: AE
A45: 门店管理 | B45: =VLOOKUP(A45,'一级菜单'!A:C,3,0) -> 3门店管理 | C45: 门店装修 | D45: =B45&"_"&F45 -> 3门店管理_11 | E45: =A45&"/"&C45 -> 门店管理/门店装修 | F45: =VLOOKUP(C45,'一级菜单'!F:G,2,0) -> 11 | G45: =D45&"_"&I45 -> 3门店管理_11_41 | H45: 门店装修额内兑现 | I45: =VLOOKUP(H45,'一级菜单'!H:I,2,0) -> 41 | J45: =B45&"_"&F45&"_"&I45 -> 3门店管理_11_41 | K45: 是 | L45: AE
A46: 门店管理 | B46: =VLOOKUP(A46,'一级菜单'!A:C,3,0) -> 3门店管理 | C46: 门店装修 | D46: =B46&"_"&F46 -> 3门店管理_11 | E46: =A46&"/"&C46 -> 门店管理/门店装修 | F46: =VLOOKUP(C46,'一级菜单'!F:G,2,0) -> 11 | G46: =D46&"_"&I46 -> 3门店管理_11_42 | H46: 额度内兑现批量复核 | I46: =VLOOKUP(H46,'一级菜单'!H:I,2,0) -> 42 | J46: =B46&"_"&F46&"_"&I46 -> 3门店管理_11_42 | K46: 财务 | L46: AE
A47: 门店管理 | B47: =VLOOKUP(A47,'一级菜单'!A:C,3,0) -> 3门店管理 | C47: 门店装修 | D47: =B47&"_"&F47 -> 3门店管理_11 | E47: =A47&"/"&C47 -> 门店管理/门店装修 | F47: =VLOOKUP(C47,'一级菜单'!F:G,2,0) -> 11 | G47: =D47&"_"&I47 -> 3门店管理_11_43 | H47: 门店装修额外兑现 | I47: =VLOOKUP(H47,'一级菜单'!H:I,2,0) -> 43 | J47: =B47&"_"&F47&"_"&I47 -> 3门店管理_11_43 | K47: 是 | L47: AE
A48: 门店管理 | B48: =VLOOKUP(A48,'一级菜单'!A:C,3,0) -> 3门店管理 | C48: 门店装修 | D48: =B48&"_"&F48 -> 3门店管理_11 | E48: =A48&"/"&C48 -> 门店管理/门店装修 | F48: =VLOOKUP(C48,'一级菜单'!F:G,2,0) -> 11 | G48: =D48&"_"&I48 -> 3门店管理_11_44 | H48: 门店装修申请变更 | I48: =VLOOKUP(H48,'一级菜单'!H:I,2,0) -> 44 | J48: =B48&"_"&F48&"_"&I48 -> 3门店管理_11_44 | K48: 是 | L48: AE
A49: 门店管理 | B49: =VLOOKUP(A49,'一级菜单'!A:C,3,0) -> 3门店管理 | C49: 门店装修 | D49: =B49&"_"&F49 -> 3门店管理_11 | E49: =A49&"/"&C49 -> 门店管理/门店装修 | F49: =VLOOKUP(C49,'一级菜单'!F:G,2,0) -> 11 | G49: =D49&"_"&I49 -> 3门店管理_11_45 | H49: 门店装修申请关闭 | I49: =VLOOKUP(H49,'一级菜单'!H:I,2,0) -> 45 | J49: =B49&"_"&F49&"_"&I49 -> 3门店管理_11_45 | K49: 是 | L49: AE
A50: 门店管理 | B50: =VLOOKUP(A50,'一级菜单'!A:C,3,0) -> 3门店管理 | C50: 门店装修 | D50: =B50&"_"&F50 -> 3门店管理_11 | E50: =A50&"/"&C50 -> 门店管理/门店装修 | F50: =VLOOKUP(C50,'一级菜单'!F:G,2,0) -> 11 | G50: =D50&"_"&I50 -> 3门店管理_11_46 | H50: 门头展板报销申请-新 | I50: =VLOOKUP(H50,'一级菜单'!H:I,2,0) -> 46 | J50: =B50&"_"&F50&"_"&I50 -> 3门店管理_11_46 | K50: 是 | L50: AE
A51: 门店管理 | B51: =VLOOKUP(A51,'一级菜单'!A:C,3,0) -> 3门店管理 | C51: 门店装修 | D51: =B51&"_"&F51 -> 3门店管理_11 | E51: =A51&"/"&C51 -> 门店管理/门店装修 | F51: =VLOOKUP(C51,'一级菜单'!F:G,2,0) -> 11 | G51: =D51&"_"&I51 -> 3门店管理_11_47 | H51: 门头展板兑现申请-新 | I51: =VLOOKUP(H51,'一级菜单'!H:I,2,0) -> 47 | J51: =B51&"_"&F51&"_"&I51 -> 3门店管理_11_47 | K51: 是 | L51: AE
A52: 门店管理 | B52: =VLOOKUP(A52,'一级菜单'!A:C,3,0) -> 3门店管理 | C52: 广告投放 | D52: =B52&"_"&F52 -> 3门店管理_12 | E52: =A52&"/"&C52 -> 门店管理/广告投放 | F52: =VLOOKUP(C52,'一级菜单'!F:G,2,0) -> 12 | G52: =D52&"_"&I52 -> 3门店管理_12_48 | H52: 广告投放申请 | I52: =VLOOKUP(H52,'一级菜单'!H:I,2,0) -> 48 | J52: =B52&"_"&F52&"_"&I52 -> 3门店管理_12_48 | K52: 是 | L52: AE
A53: 门店管理 | B53: =VLOOKUP(A53,'一级菜单'!A:C,3,0) -> 3门店管理 | C53: 广告投放 | D53: =B53&"_"&F53 -> 3门店管理_12 | E53: =A53&"/"&C53 -> 门店管理/广告投放 | F53: =VLOOKUP(C53,'一级菜单'!F:G,2,0) -> 12 | G53: =D53&"_"&I53 -> 3门店管理_12_49 | H53: 广告费报销 | I53: =VLOOKUP(H53,'一级菜单'!H:I,2,0) -> 49 | J53: =B53&"_"&F53&"_"&I53 -> 3门店管理_12_49 | K53: 是 | L53: AE
A54: 门店管理 | B54: =VLOOKUP(A54,'一级菜单'!A:C,3,0) -> 3门店管理 | C54: 广告投放 | D54: =B54&"_"&F54 -> 3门店管理_12 | E54: =A54&"/"&C54 -> 门店管理/广告投放 | F54: =VLOOKUP(C54,'一级菜单'!F:G,2,0) -> 12 | G54: =D54&"_"&I54 -> 3门店管理_12_50 | H54: 广告报销兑现 | I54: =VLOOKUP(H54,'一级菜单'!H:I,2,0) -> 50 | J54: =B54&"_"&F54&"_"&I54 -> 3门店管理_12_50 | K54: 是 | L54: AE
... A105: 工程管理 | B105: =VLOOKUP(A105,'一级菜单'!A:C,3,0) -> 4工程管理 | C105: 真实性核销 | D105: =B105&"_"&F105 -> 4工程管理_20 | E105: =A105&"/"&C105 -> 工程管理/真实性核销 | F105: =VLOOKUP(C105,'一级菜单'!F:G,2,0) -> 20 | G105: =D105&"_"&I105 -> 4工程管理_20_99 | H105: 取消核销和发票作废（工程） | I105: =VLOOKUP(H105,'一级菜单'!H:I,2,0) -> 99 | J105: =B105&"_"&F105&"_"&I105 -> 4工程管理_20_99 | K105: 是 | L105: AE
A106: 工程管理 | B106: =VLOOKUP(A106,'一级菜单'!A:C,3,0) -> 4工程管理 | C106: 真实性核销 | D106: =B106&"_"&F106 -> 4工程管理_20 | E106: =A106&"/"&C106 -> 工程管理/真实性核销 | F106: =VLOOKUP(C106,'一级菜单'!F:G,2,0) -> 20 | G106: =D106&"_"&I106 -> 4工程管理_20_100 | H106: 核销发票上传明细报表 | I106: =VLOOKUP(H106,'一级菜单'!H:I,2,0) -> 100 | J106: =B106&"_"&F106&"_"&I106 -> 4工程管理_20_100 | L106: AE
A107: 工程管理 | B107: =VLOOKUP(A107,'一级菜单'!A:C,3,0) -> 4工程管理 | C107: 真实性核销 | D107: =B107&"_"&F107 -> 4工程管理_20 | E107: =A107&"/"&C107 -> 工程管理/真实性核销 | F107: =VLOOKUP(C107,'一级菜单'!F:G,2,0) -> 20 | G107: =D107&"_"&I107 -> 4工程管理_20_101 | H107: 工程真实性核销明细报表 | I107: =VLOOKUP(H107,'一级菜单'!H:I,2,0) -> 101 | J107: =B107&"_"&F107&"_"&I107 -> 4工程管理_20_101 | K107: 是 | L107: AE
A108: 工程管理 | B108: =VLOOKUP(A108,'一级菜单'!A:C,3,0) -> 4工程管理 | C108: 真实性核销 | D108: =B108&"_"&F108 -> 4工程管理_20 | E108: =A108&"/"&C108 -> 工程管理/真实性核销 | F108: =VLOOKUP(C108,'一级菜单'!F:G,2,0) -> 20 | G108: =D108&"_"&I108 -> #N/A | H108: 真实性核销抬价返还报表（工程,家装） | I108: =VLOOKUP(H108,'一级菜单'!H:I,2,0) -> #N/A | J108: =B108&"_"&F108&"_"&I108 -> #N/A | L108: AE
A109: 工程管理 | B109: =VLOOKUP(A109,'一级菜单'!A:C,3,0) -> 4工程管理 | C109: 真实性核销 | D109: =B109&"_"&F109 -> 4工程管理_20 | E109: =A109&"/"&C109 -> 工程管理/真实性核销 | F109: =VLOOKUP(C109,'一级菜单'!F:G,2,0) -> 20 | G109: =D109&"_"&I109 -> 4工程管理_20_103 | H109: 真实性核销抬价返还明细报表（家装） | I109: =VLOOKUP(H109,'一级菜单'!H:I,2,0) -> 103 | J109: =B109&"_"&F109&"_"&I109 -> 4工程管理_20_103 | L109: AE
A110: 工程管理 | B110: =VLOOKUP(A110,'一级菜单'!A:C,3,0) -> 4工程管理 | C110: 报表中心 | D110: =B110&"_"&F110 -> 4工程管理_21 | E110: =A110&"/"&C110 -> 工程管理/报表中心 | F110: =VLOOKUP(C110,'一级菜单'!F:G,2,0) -> 21 | G110: =D110&"_"&I110 -> 4工程管理_21_104 | H110: 工程项目透视 | I110: =VLOOKUP(H110,'一级菜单'!H:I,2,0) -> 104 | J110: =B110&"_"&F110&"_"&I110 -> 4工程管理_21_104 | K110: 是 | L110: AE
A111: 工程管理 | B111: =VLOOKUP(A111,'一级菜单'!A:C,3,0) -> 4工程管理 | C111: 报表中心 | D111: =B111&"_"&F111 -> 4工程管理_21 | E111: =A111&"/"&C111 -> 工程管理/报表中心 | F111: =VLOOKUP(C111,'一级菜单'!F:G,2,0) -> 21 | G111: =D111&"_"&I111 -> 4工程管理_21_105 | H111: 合同完成率分析 | I111: =VLOOKUP(H111,'一级菜单'!H:I,2,0) -> 105 | J111: =B111&"_"&F111&"_"&I111 -> 4工程管理_21_105 | K111: 是 | L111: AE
A112: 工程管理 | B112: =VLOOKUP(A112,'一级菜单'!A:C,3,0) -> 4工程管理 | C112: 报表中心 | D112: =B112&"_"&F112 -> 4工程管理_21 | E112: =A112&"/"&C112 -> 工程管理/报表中心 | F112: =VLOOKUP(C112,'一级菜单'!F:G,2,0) -> 21 | G112: =D112&"_"&I112 -> 4工程管理_21_106 | H112: 工程服务费兑现报表 | I112: =VLOOKUP(H112,'一级菜单'!H:I,2,0) -> 106 | J112: =B112&"_"&F112&"_"&I112 -> 4工程管理_21_106 | K112: 财务 | L112: AE
A113: 工程管理 | B113: =VLOOKUP(A113,'一级菜单'!A:C,3,0) -> 4工程管理 | C113: 报表中心 | D113: =B113&"_"&F113 -> 4工程管理_21 | E113: =A113&"/"&C113 -> 工程管理/报表中心 | F113: =VLOOKUP(C113,'一级菜单'!F:G,2,0) -> 21 | G113: =D113&"_"&I113 -> 4工程管理_21_107 | H113: 工程服务费签收报表 | I113: =VLOOKUP(H113,'一级菜单'!H:I,2,0) -> 107 | J113: =B113&"_"&F113&"_"&I113 -> 4工程管理_21_107 | K113: 财务 | L113: AE
A114: 工程管理 | B114: =VLOOKUP(A114,'一级菜单'!A:C,3,0) -> 4工程管理 | C114: 报表中心 | D114: =B114&"_"&F114 -> 4工程管理_21 | E114: =A114&"/"&C114 -> 工程管理/报表中心 | F114: =VLOOKUP(C114,'一级菜单'!F:G,2,0) -> 21 | G114: =D114&"_"&I114 -> 4工程管理_21_108 | H114: 工程服务费计提报表 | I114: =VLOOKUP(H114,'一级菜单'!H:I,2,0) -> 108 | J114: =B114&"_"&F114&"_"&I114 -> 4工程管理_21_108 | K114: 财务 | L114: AE
A115: 工程管理 | B115: =VLOOKUP(A115,'一级菜单'!A:C,3,0) -> 4工程管理 | C115: 报表中心 | D115: =B115&"_"&F115 -> 4工程管理_21 | E115: =A115&"/"&C115 -> 工程管理/报表中心 | F115: =VLOOKUP(C115,'一级菜单'!F:G,2,0) -> 21 | G115: =D115&"_"&I115 -> 4工程管理_21_109 | H115: 已签未认领的出库单查询报表 | I115: =VLOOKUP(H115,'一级菜单'!H:I,2,0) -> 109 | J115: =B115&"_"&F115&"_"&I115 -> 4工程管理_21_109 | K115: 财务 | L115: AE
A116: 工程管理 | B116: =VLOOKUP(A116,'一级菜单'!A:C,3,0) -> 4工程管理 | C116: 报表中心 | D116: =B116&"_"&F116 -> 4工程管理_21 | E116: =A116&"/"&C116 -> 工程管理/报表中心 | F116: =VLOOKUP(C116,'一级菜单'!F:G,2,0) -> 21 | G116: =D116&"_"&I116 -> 4工程管理_21_110 | H116: 工程服务费可兑现金额报表 | I116: =VLOOKUP(H116,'一级菜单'!H:I,2,0) -> 110 | J116: =B116&"_"&F116&"_"&I116 -> 4工程管理_21_110 | K116: 财务 | L116: AE
A117: 家装管理 | B117: =VLOOKUP(A117,'一级菜单'!A:C,3,0) -> 5家装管理 | C117: 家装商机 | D117: =B117&"_"&F117 -> 5家装管理_22 | E117: =A117&"/"&C117 -> 家装管理/家装商机 | F117: =VLOOKUP(C117,'一级菜单'!F:G,2,0) -> 22 | G117: =D117&"_"&I117 -> 5家装管理_22_111 | H117: 网点信息申请 | I117: =VLOOKUP(H117,'一级菜单'!H:I,2,0) -> 111 | J117: =B117&"_"&F117&"_"&I117 -> 5家装管理_22_111 | K117: 是 | L117: AE
A118: 家装管理 | B118: =VLOOKUP(A118,'一级菜单'!A:C,3,0) -> 5家装管理 | C118: 家装商机 | D118: =B118&"_"&F118 -> 5家装管理_22 | E118: =A118&"/"&C118 -> 家装管理/家装商机 | F118: =VLOOKUP(C118,'一级菜单'!F:G,2,0) -> 22 | G118: =D118&"_"&I118 -> 5家装管理_22_112 | H118: 网点档案 | I118: =VLOOKUP(H118,'一级菜单'!H:I,2,0) -> 112 | J118: =B118&"_"&F118&"_"&I118 -> 5家装管理_22_112 | K118: 是 | L118: AE
A119: 家装管理 | B119: =VLOOKUP(A119,'一级菜单'!A:C,3,0) -> 5家装管理 | C119: 家装商机 | D119: =B119&"_"&F119 -> 5家装管理_22 | E119: =A119&"/"&C119 -> 家装管理/家装商机 | F119: =VLOOKUP(C119,'一级菜单'!F:G,2,0) -> 22 | G119: =D119&"_"&I119 -> 5家装管理_22_113 | H119: 网点变更申请 | I119: =VLOOKUP(H119,'一级菜单'!H:I,2,0) -> 113 | J119: =B119&"_"&F119&"_"&I119 -> 5家装管理_22_113 | K119: 是 | L119: AE
A120: 家装管理 | B120: =VLOOKUP(A120,'一级菜单'!A:C,3,0) -> 5家装管理 | C120: 家装商机 | D120: =B120&"_"&F120 -> 5家装管理_22 | E120: =A120&"/"&C120 -> 家装管理/家装商机 | F120: =VLOOKUP(C120,'一级菜单'!F:G,2,0) -> 22 | G120: =D120&"_"&I120 -> 5家装管理_22_114 | H120: 家装战略报备 | I120: =VLOOKUP(H120,'一级菜单'!H:I,2,0) -> 114 | J120: =B120&"_"&F120&"_"&I120 -> 5家装管理_22_114 | K120: 是 | L120: AE
A121: 家装管理 | B121: =VLOOKUP(A121,'一级菜单'!A:C,3,0) -> 5家装管理 | C121: 家装商机 | D121: =B121&"_"&F121 -> 5家装管理_22 | E121: =A121&"/"&C121 -> 家装管理/家装商机 | F121: =VLOOKUP(C121,'一级菜单'!F:G,2,0) -> 22 | G121: =D121&"_"&I121 -> 5家装管理_22_115 | H121: 家装单体报备 | I121: =VLOOKUP(H121,'一级菜单'!H:I,2,0) -> 115 | J121: =B121&"_"&F121&"_"&I121 -> 5家装管理_22_115 | K121: 是 | L121: AE
... A141: 家装管理 | B141: =VLOOKUP(A141,'一级菜单'!A:C,3,0) -> 5家装管理 | C141: 真实性核销 | D141: =B141&"_"&F141 -> 5家装管理_20 | E141: =A141&"/"&C141 -> 家装管理/真实性核销 | F141: =VLOOKUP(C141,'一级菜单'!F:G,2,0) -> 20 | G141: =D141&"_"&I141 -> 5家装管理_20_135 | H141: 取消核销和发票作废（家装） | I141: =VLOOKUP(H141,'一级菜单'!H:I,2,0) -> 135 | J141: =B141&"_"&F141&"_"&I141 -> 5家装管理_20_135 | K141: 是 | L141: AE
A142: 家装管理 | B142: =VLOOKUP(A142,'一级菜单'!A:C,3,0) -> 5家装管理 | C142: 真实性核销 | D142: =B142&"_"&F142 -> 5家装管理_20 | E142: =A142&"/"&C142 -> 家装管理/真实性核销 | F142: =VLOOKUP(C142,'一级菜单'!F:G,2,0) -> 20 | G142: =D142&"_"&I142 -> 5家装管理_20_136 | H142: 家装核销发票上传明细报表 | I142: =VLOOKUP(H142,'一级菜单'!H:I,2,0) -> 136 | J142: =B142&"_"&F142&"_"&I142 -> 5家装管理_20_136 | L142: AE
A143: 家装管理 | B143: =VLOOKUP(A143,'一级菜单'!A:C,3,0) -> 5家装管理 | C143: 真实性核销 | D143: =B143&"_"&F143 -> 5家装管理_20 | E143: =A143&"/"&C143 -> 家装管理/真实性核销 | F143: =VLOOKUP(C143,'一级菜单'!F:G,2,0) -> 20 | G143: =D143&"_"&I143 -> 5家装管理_20_137 | H143: 家装真实性核销明细报表 | I143: =VLOOKUP(H143,'一级菜单'!H:I,2,0) -> 137 | J143: =B143&"_"&F143&"_"&I143 -> 5家装管理_20_137 | K143: 是 | L143: AE
A144: 折扣政策 | B144: =VLOOKUP(A144,'一级菜单'!A:C,3,0) -> 6折扣政策 | C144: 样品及长库龄折扣政策申请 | D144: =B144&"_"&F144 -> 6折扣政策_25 | E144: =A144&"/"&C144 -> 折扣政策/样品及长库龄折扣政策申请 | F144: =VLOOKUP(C144,'一级菜单'!F:G,2,0) -> 25 | G144: =D144&"_"&I144 -> #N/A | I144: =VLOOKUP(H144,'一级菜单'!H:I,2,0) -> #N/A | J144: =B144&"_"&F144&"_"&I144 -> #N/A | K144: 是 | L144: AE
A145: 折扣政策 | B145: =VLOOKUP(A145,'一级菜单'!A:C,3,0) -> 6折扣政策 | C145: 样品及长库龄折扣政策失效 | D145: =B145&"_"&F145 -> 6折扣政策_26 | E145: =A145&"/"&C145 -> 折扣政策/样品及长库龄折扣政策失效 | F145: =VLOOKUP(C145,'一级菜单'!F:G,2,0) -> 26 | G145: =D145&"_"&I145 -> #N/A | I145: =VLOOKUP(H145,'一级菜单'!H:I,2,0) -> #N/A | J145: =B145&"_"&F145&"_"&I145 -> #N/A | K145: 是 | L145: CRM,AE
A146: 折扣政策 | B146: =VLOOKUP(A146,'一级菜单'!A:C,3,0) -> 6折扣政策 | C146: 折扣政策申请 | D146: =B146&"_"&F146 -> 6折扣政策_27 | E146: =A146&"/"&C146 -> 折扣政策/折扣政策申请 | F146: =VLOOKUP(C146,'一级菜单'!F:G,2,0) -> 27 | G146: =D146&"_"&I146 -> #N/A | I146: =VLOOKUP(H146,'一级菜单'!H:I,2,0) -> #N/A | J146: =B146&"_"&F146&"_"&I146 -> #N/A | K146: 是 | L146: CRM
A147: 折扣政策 | B147: =VLOOKUP(A147,'一级菜单'!A:C,3,0) -> 6折扣政策 | C147: 折扣政策失效 | D147: =B147&"_"&F147 -> 6折扣政策_28 | E147: =A147&"/"&C147 -> 折扣政策/折扣政策失效 | F147: =VLOOKUP(C147,'一级菜单'!F:G,2,0) -> 28 | G147: =D147&"_"&I147 -> #N/A | I147: =VLOOKUP(H147,'一级菜单'!H:I,2,0) -> #N/A | J147: =B147&"_"&F147&"_"&I147 -> #N/A | K147: 是 | L147: CRM,AE
A148: 折扣政策 | B148: =VLOOKUP(A148,'一级菜单'!A:C,3,0) -> 6折扣政策 | C148: 折扣政策明细查询 | D148: =B148&"_"&F148 -> 6折扣政策_29 | E148: =A148&"/"&C148 -> 折扣政策/折扣政策明细查询 | F148: =VLOOKUP(C148,'一级菜单'!F:G,2,0) -> 29 | G148: =D148&"_"&I148 -> #N/A | I148: =VLOOKUP(H148,'一级菜单'!H:I,2,0) -> #N/A | J148: =B148&"_"&F148&"_"&I148 -> #N/A | K148: 是 | L148: CRM,AE
A149: 采购订单 | B149: =VLOOKUP(A149,'一级菜单'!A:C,3,0) -> 7采购订单 | C149: 订单查询 | D149: =B149&"_"&F149 -> 7采购订单_30 | E149: =A149&"/"&C149 -> 采购订单/订单查询 | F149: =VLOOKUP(C149,'一级菜单'!F:G,2,0) -> 30 | G149: =D149&"_"&I149 -> 7采购订单_30_138 | H149: 订单查询 | I149: =VLOOKUP(H149,'一级菜单'!H:I,2,0) -> 138 | J149: =B149&"_"&F149&"_"&I149 -> 7采购订单_30_138 | K149: 是 | L149: CRM,AE
A150: 采购订单 | B150: =VLOOKUP(A150,'一级菜单'!A:C,3,0) -> 7采购订单 | C150: 订单查询 | D150: =B150&"_"&F150 -> 7采购订单_30 | E150: =A150&"/"&C150 -> 采购订单/订单查询 | F150: =VLOOKUP(C150,'一级菜单'!F:G,2,0) -> 30 | G150: =D150&"_"&I150 -> 7采购订单_30_139 | H150: 定制订单进度表查询 | I150: =VLOOKUP(H150,'一级菜单'!H:I,2,0) -> 139 | J150: =B150&"_"&F150&"_"&I150 -> 7采购订单_30_139 | L150: CRM
A151: 采购订单 | B151: =VLOOKUP(A151,'一级菜单'!A:C,3,0) -> 7采购订单 | C151: 订单查询 | D151: =B151&"_"&F151 -> 7采购订单_30 | E151: =A151&"/"&C151 -> 采购订单/订单查询 | F151: =VLOOKUP(C151,'一级菜单'!F:G,2,0) -> 30 | G151: =D151&"_"&I151 -> 7采购订单_30_140 | H151: 审核未发运查询 | I151: =VLOOKUP(H151,'一级菜单'!H:I,2,0) -> 140 | J151: =B151&"_"&F151&"_"&I151 -> 7采购订单_30_140 | L151: CRM
A152: 采购订单 | B152: =VLOOKUP(A152,'一级菜单'!A:C,3,0) -> 7采购订单 | C152: 订单查询 | D152: =B152&"_"&F152 -> 7采购订单_30 | E152: =A152&"/"&C152 -> 采购订单/订单查询 | F152: =VLOOKUP(C152,'一级菜单'!F:G,2,0) -> 30 | G152: =D152&"_"&I152 -> 7采购订单_30_141 | H152: 占用定金明细报表 | I152: =VLOOKUP(H152,'一级菜单'!H:I,2,0) -> 141 | J152: =B152&"_"&F152&"_"&I152 -> 7采购订单_30_141 | K152: 是 | L152: CRM
A153: 采购订单 | B153: =VLOOKUP(A153,'一级菜单'!A:C,3,0) -> 7采购订单 | C153: 出库单查询 | D153: =B153&"_"&F153 -> 7采购订单_31 | E153: =A153&"/"&C153 -> 采购订单/出库单查询 | F153: =VLOOKUP(C153,'一级菜单'!F:G,2,0) -> 31 | G153: =D153&"_"&I153 -> #N/A | I153: =VLOOKUP(H153,'一级菜单'!H:I,2,0) -> #N/A | J153: =B153&"_"&F153&"_"&I153 -> #N/A | K153: 是 | L153: CRM,AE,MBO
A154: 采购订单 | B154: =VLOOKUP(A154,'一级菜单'!A:C,3,0) -> 7采购订单 | C154: 订单创建 | D154: =B154&"_"&F154 -> 7采购订单_32 | E154: =A154&"/"&C154 -> 采购订单/订单创建 | F154: =VLOOKUP(C154,'一级菜单'!F:G,2,0) -> 32 | G154: =D154&"_"&I154 -> 7采购订单_32_142 | H154: 计划订单 | I154: =VLOOKUP(H154,'一级菜单'!H:I,2,0) -> 142 | J154: =B154&"_"&F154&"_"&I154 -> 7采购订单_32_142 | K154: 是 | L154: CRM
A155: 采购订单 | B155: =VLOOKUP(A155,'一级菜单'!A:C,3,0) -> 7采购订单 | C155: 订单创建 | D155: =B155&"_"&F155 -> 7采购订单_32 | E155: =A155&"/"&C155 -> 采购订单/订单创建 | F155: =VLOOKUP(C155,'一级菜单'!F:G,2,0) -> 32 | G155: =D155&"_"&I155 -> 7采购订单_32_143 | H155: 常规订单 | I155: =VLOOKUP(H155,'一级菜单'!H:I,2,0) -> 143 | J155: =B155&"_"&F155&"_"&I155 -> 7采购订单_32_143 | K155: 是 | L155: CRM
A156: 采购订单 | B156: =VLOOKUP(A156,'一级菜单'!A:C,3,0) -> 7采购订单 | C156: 订单创建 | D156: =B156&"_"&F156 -> 7采购订单_32 | E156: =A156&"/"&C156 -> 采购订单/订单创建 | F156: =VLOOKUP(C156,'一级菜单'!F:G,2,0) -> 32 | G156: =D156&"_"&I156 -> 7采购订单_32_144 | H156: 定制订单 | I156: =VLOOKUP(H156,'一级菜单'!H:I,2,0) -> 144 | J156: =B156&"_"&F156&"_"&I156 -> 7采购订单_32_144 | K156: 是 | L156: CRM
A157: 采购订单 | B157: =VLOOKUP(A157,'一级菜单'!A:C,3,0) -> 7采购订单 | C157: 订单创建 | D157: =B157&"_"&F157 -> 7采购订单_32 | E157: =A157&"/"&C157 -> 采购订单/订单创建 | F157: =VLOOKUP(C157,'一级菜单'!F:G,2,0) -> 32 | G157: =D157&"_"&I157 -> 7采购订单_32_145 | H157: 样品及长库龄订单 | I157: =VLOOKUP(H157,'一级菜单'!H:I,2,0) -> 145 | J157: =B157&"_"&F157&"_"&I157 -> 7采购订单_32_145 | K157: 是 | L157: AE
A158: 采购订单 | B158: =VLOOKUP(A158,'一级菜单'!A:C,3,0) -> 7采购订单 | C158: 订单创建 | D158: =B158&"_"&F158 -> 7采购订单_32 | E158: =A158&"/"&C158 -> 采购订单/订单创建 | F158: =VLOOKUP(C158,'一级菜单'!F:G,2,0) -> 32 | G158: =D158&"_"&I158 -> 7采购订单_32_146 | H158: 广告物料订单 | I158: =VLOOKUP(H158,'一级菜单'!H:I,2,0) -> 146 | J158: =B158&"_"&F158&"_"&I158 -> 7采购订单_32_146 | K158: 是 | L158: CRM
A159: 采购订单 | B159: =VLOOKUP(A159,'一级菜单'!A:C,3,0) -> 7采购订单 | C159: 订单创建 | D159: =B159&"_"&F159 -> 7采购订单_32 | E159: =A159&"/"&C159 -> 采购订单/订单创建 | F159: =VLOOKUP(C159,'一级菜单'!F:G,2,0) -> 32 | G159: =D159&"_"&I159 -> 7采购订单_32_147 | H159: 转卖订单 | I159: =VLOOKUP(H159,'一级菜单'!H:I,2,0) -> 147 | J159: =B159&"_"&F159&"_"&I159 -> 7采购订单_32_147 | L159: CRM
A160: 采购订单 | B160: =VLOOKUP(A160,'一级菜单'!A:C,3,0) -> 7采购订单 | C160: 出口订单创建 | D160: =B160&"_"&F160 -> 7采购订单_33 | E160: =A160&"/"&C160 -> 采购订单/出口订单创建 | F160: =VLOOKUP(C160,'一级菜单'!F:G,2,0) -> 33 | G160: =D160&"_"&I160 -> 7采购订单_33_148 | H160: 出口计划订单 | I160: =VLOOKUP(H160,'一级菜单'!H:I,2,0) -> 148 | J160: =B160&"_"&F160&"_"&I160 -> 7采购订单_33_148 | L160: CRM
A161: 采购订单 | B161: =VLOOKUP(A161,'一级菜单'!A:C,3,0) -> 7采购订单 | C161: 出口订单创建 | D161: =B161&"_"&F161 -> 7采购订单_33 | E161: =A161&"/"&C161 -> 采购订单/出口订单创建 | F161: =VLOOKUP(C161,'一级菜单'!F:G,2,0) -> 33 | G161: =D161&"_"&I161 -> 7采购订单_33_149 | H161: 出口常规订单 | I161: =VLOOKUP(H161,'一级菜单'!H:I,2,0) -> 149 | J161: =B161&"_"&F161&"_"&I161 -> 7采购订单_33_149 | L161: CRM
A162: 采购订单 | B162: =VLOOKUP(A162,'一级菜单'!A:C,3,0) -> 7采购订单 | C162: 出口订单创建 | D162: =B162&"_"&F162 -> 7采购订单_33 | E162: =A162&"/"&C162 -> 采购订单/出口订单创建 | F162: =VLOOKUP(C162,'一级菜单'!F:G,2,0) -> 33 | G162: =D162&"_"&I162 -> 7采购订单_33_150 | H162: 出口定制订单 | I162: =VLOOKUP(H162,'一级菜单'!H:I,2,0) -> 150 | J162: =B162&"_"&F162&"_"&I162 -> 7采购订单_33_150 | L162: CRM
A163: 采购订单 | B163: =VLOOKUP(A163,'一级菜单'!A:C,3,0) -> 7采购订单 | C163: 出口订单创建 | D163: =B163&"_"&F163 -> 7采购订单_33 | E163: =A163&"/"&C163 -> 采购订单/出口订单创建 | F163: =VLOOKUP(C163,'一级菜单'!F:G,2,0) -> 33 | G163: =D163&"_"&I163 -> 7采购订单_33_151 | H163: 成品出口退货订单 | I163: =VLOOKUP(H163,'一级菜单'!H:I,2,0) -> 151 | J163: =B163&"_"&F163&"_"&I163 -> 7采购订单_33_151 | L163: CRM
A164: 采购订单 | B164: =VLOOKUP(A164,'一级菜单'!A:C,3,0) -> 7采购订单 | C164: 发货跟踪 | D164: =B164&"_"&F164 -> 7采购订单_34 | E164: =A164&"/"&C164 -> 采购订单/发货跟踪 | F164: =VLOOKUP(C164,'一级菜单'!F:G,2,0) -> 34 | G164: =D164&"_"&I164 -> 7采购订单_34_152 | H164: 发运确认 | I164: =VLOOKUP(H164,'一级菜单'!H:I,2,0) -> 152 | J164: =B164&"_"&F164&"_"&I164 -> 7采购订单_34_152 | L164: MBO
A165: 采购订单 | B165: =VLOOKUP(A165,'一级菜单'!A:C,3,0) -> 7采购订单 | C165: 发货跟踪 | D165: =B165&"_"&F165 -> 7采购订单_34 | E165: =A165&"/"&C165 -> 采购订单/发货跟踪 | F165: =VLOOKUP(C165,'一级菜单'!F:G,2,0) -> 34 | G165: =D165&"_"&I165 -> 7采购订单_34_153 | H165: 收货确认 | I165: =VLOOKUP(H165,'一级菜单'!H:I,2,0) -> 153 | J165: =B165&"_"&F165&"_"&I165 -> 7采购订单_34_153 | L165: MBO
A166: 采购订单 | B166: =VLOOKUP(A166,'一级菜单'!A:C,3,0) -> 7采购订单 | C166: 发货跟踪 | D166: =B166&"_"&F166 -> 7采购订单_34 | E166: =A166&"/"&C166 -> 采购订单/发货跟踪 | F166: =VLOOKUP(C166,'一级菜单'!F:G,2,0) -> 34 | G166: =D166&"_"&I166 -> 7采购订单_34_154 | H166: 采购单发运跟踪 | I166: =VLOOKUP(H166,'一级菜单'!H:I,2,0) -> 154 | J166: =B166&"_"&F166&"_"&I166 -> 7采购订单_34_154 | L166: MBO
A167: 采购订单 | B167: =VLOOKUP(A167,'一级菜单'!A:C,3,0) -> 7采购订单 | C167: 发货跟踪 | D167: =B167&"_"&F167 -> 7采购订单_34 | E167: =A167&"/"&C167 -> 采购订单/发货跟踪 | F167: =VLOOKUP(C167,'一级菜单'!F:G,2,0) -> 34 | G167: =D167&"_"&I167 -> 7采购订单_34_155 | H167: 出库单发运跟踪 | I167: =VLOOKUP(H167,'一级菜单'!H:I,2,0) -> 155 | J167: =B167&"_"&F167&"_"&I167 -> 7采购订单_34_155 | L167: MBO
A168: 采购订单 | B168: =VLOOKUP(A168,'一级菜单'!A:C,3,0) -> 7采购订单 | C168: 发货跟踪 | D168: =B168&"_"&F168 -> 7采购订单_34 | E168: =A168&"/"&C168 -> 采购订单/发货跟踪 | F168: =VLOOKUP(C168,'一级菜单'!F:G,2,0) -> 34 | G168: =D168&"_"&I168 -> 7采购订单_34_156 | H168: 异常反馈发起 | I168: =VLOOKUP(H168,'一级菜单'!H:I,2,0) -> 156 | J168: =B168&"_"&F168&"_"&I168 -> 7采购订单_34_156 | L168: MBO
A169: 采购订单 | B169: =VLOOKUP(A169,'一级菜单'!A:C,3,0) -> 7采购订单 | C169: 发货跟踪 | D169: =B169&"_"&F169 -> 7采购订单_34 | E169: =A169&"/"&C169 -> 采购订单/发货跟踪 | F169: =VLOOKUP(C169,'一级菜单'!F:G,2,0) -> 34 | G169: =D169&"_"&I169 -> 7采购订单_34_157 | H169: 异常反馈结果查询 | I169: =VLOOKUP(H169,'一级菜单'!H:I,2,0) -> 157 | J169: =B169&"_"&F169&"_"&I169 -> 7采购订单_34_157 | L169: MBO
A170: 采购订单 | B170: =VLOOKUP(A170,'一级菜单'!A:C,3,0) -> 7采购订单 | C170: 发货跟踪 | D170: =B170&"_"&F170 -> 7采购订单_34 | E170: =A170&"/"&C170 -> 采购订单/发货跟踪 | F170: =VLOOKUP(C170,'一级菜单'!F:G,2,0) -> 34 | G170: =D170&"_"&I170 -> 7采购订单_34_158 | H170: 异常费用查询 | I170: =VLOOKUP(H170,'一级菜单'!H:I,2,0) -> 158 | J170: =B170&"_"&F170&"_"&I170 -> 7采购订单_34_158 | L170: MBO
... A173: 采购订单 | B173: =VLOOKUP(A173,'一级菜单'!A:C,3,0) -> 7采购订单 | C173: 退货订单 | D173: =B173&"_"&F173 -> 7采购订单_35 | E173: =A173&"/"&C173 -> 采购订单/退货订单 | F173: =VLOOKUP(C173,'一级菜单'!F:G,2,0) -> 35 | G173: =D173&"_"&I173 -> 7采购订单_35_161 | H173: 退货申请单查询 | I173: =VLOOKUP(H173,'一级菜单'!H:I,2,0) -> 161 | J173: =B173&"_"&F173&"_"&I173 -> 7采购订单_35_161 | L173: CRM,AE
A174: 采购订单 | B174: =VLOOKUP(A174,'一级菜单'!A:C,3,0) -> 7采购订单 | C174: 退货订单 | D174: =B174&"_"&F174 -> 7采购订单_35 | E174: =A174&"/"&C174 -> 采购订单/退货订单 | F174: =VLOOKUP(C174,'一级菜单'!F:G,2,0) -> 35 | G174: =D174&"_"&I174 -> 7采购订单_35_162 | H174: 退货明细查询 | I174: =VLOOKUP(H174,'一级菜单'!H:I,2,0) -> 162 | J174: =B174&"_"&F174&"_"&I174 -> 7采购订单_35_162 | K174: 是 | L174: CRM,AE
A175: 采购订单 | B175: =VLOOKUP(A175,'一级菜单'!A:C,3,0) -> 7采购订单 | C175: 退货订单 | D175: =B175&"_"&F175 -> 7采购订单_35 | E175: =A175&"/"&C175 -> 采购订单/退货订单 | F175: =VLOOKUP(C175,'一级菜单'!F:G,2,0) -> 35 | G175: =D175&"_"&I175 -> 7采购订单_35_163 | H175: 广告物料退货订单 | I175: =VLOOKUP(H175,'一级菜单'!H:I,2,0) -> 163 | J175: =B175&"_"&F175&"_"&I175 -> 7采购订单_35_163 | L175: CRM
A176: 采购订单 | B176: =VLOOKUP(A176,'一级菜单'!A:C,3,0) -> 7采购订单 | C176: 退货订单 | D176: =B176&"_"&F176 -> 7采购订单_35 | E176: =A176&"/"&C176 -> 采购订单/退货订单 | F176: =VLOOKUP(C176,'一级菜单'!F:G,2,0) -> 35 | G176: =D176&"_"&I176 -> 7采购订单_35_164 | H176: 成品退货订单 | I176: =VLOOKUP(H176,'一级菜单'!H:I,2,0) -> 164 | J176: =B176&"_"&F176&"_"&I176 -> 7采购订单_35_164 | K176: 是 | L176: CRM,AE
A177: 采购订单 | B177: =VLOOKUP(A177,'一级菜单'!A:C,3,0) -> 7采购订单 | C177: 退货订单 | D177: =B177&"_"&F177 -> 7采购订单_35 | E177: =A177&"/"&C177 -> 采购订单/退货订单 | F177: =VLOOKUP(C177,'一级菜单'!F:G,2,0) -> 35 | G177: =D177&"_"&I177 -> 7采购订单_35_165 | H177: 配件退货订单 | I177: =VLOOKUP(H177,'一级菜单'!H:I,2,0) -> 165 | J177: =B177&"_"&F177&"_"&I177 -> 7采购订单_35_165 | K177: 是，未来 | L177: CRM
A178: 采购订单 | B178: =VLOOKUP(A178,'一级菜单'!A:C,3,0) -> 7采购订单 | C178: 退货订单 | D178: =B178&"_"&F178 -> 7采购订单_35 | E178: =A178&"/"&C178 -> 采购订单/退货订单 | F178: =VLOOKUP(C178,'一级菜单'!F:G,2,0) -> 35 | G178: =D178&"_"&I178 -> 7采购订单_35_166 | H178: 废料退货订单 | I178: =VLOOKUP(H178,'一级菜单'!H:I,2,0) -> 166 | J178: =B178&"_"&F178&"_"&I178 -> 7采购订单_35_166 | K178: 是，未来 | L178: CRM
A179: 采购订单 | B179: =VLOOKUP(A179,'一级菜单'!A:C,3,0) -> 7采购订单 | C179: 退货订单 | D179: =B179&"_"&F179 -> 7采购订单_35 | E179: =A179&"/"&C179 -> 采购订单/退货订单 | F179: =VLOOKUP(C179,'一级菜单'!F:G,2,0) -> 35 | G179: =D179&"_"&I179 -> 7采购订单_35_167 | H179: 转卖退货订单 | I179: =VLOOKUP(H179,'一级菜单'!H:I,2,0) -> 167 | J179: =B179&"_"&F179&"_"&I179 -> 7采购订单_35_167 | K179: 是，未来 | L179: CRM
A180: 经销商库存 | B180: =VLOOKUP(A180,'一级菜单'!A:C,3,0) -> 8经销商库存 | C180: 月度库存上传 | D180: =B180&"_"&F180 -> 8经销商库存_36 | E180: =A180&"/"&C180 -> 经销商库存/月度库存上传 | F180: =VLOOKUP(C180,'一级菜单'!F:G,2,0) -> 36 | G180: =D180&"_"&I180 -> #N/A | I180: =VLOOKUP(H180,'一级菜单'!H:I,2,0) -> #N/A | J180: =B180&"_"&F180&"_"&I180 -> #N/A | L180: CRM
...

Sheet CRM计划菜单
A1: 序号 | B1: 进度 | C1: 适用对象 | D1: 一级菜单 | E1: 二级菜单 | G1: 预估人天 | H1: 备注
A2: 1 | B2: 开发中 | C2: CRM-经销商账号 | D2: 首页 | F2: =D2&E2 -> 首页
A3: 2 | B3: 开发中 | C3: CRM-经销商账号 | D3: 我的导入（异步） | F3: =D3&E3 -> 我的导入（异步）
A4: 3 | B4: 开发中 | C4: CRM-经销商账号 | D4: 我的导出（异步） | F4: =D4&E4 -> 我的导出（异步）
A5: 4 | B5: 开发中 | C5: CRM-经销商账号/内部用户 | D5: 经销商 | F5: =D5&E5 -> 经销商
A6: 5 | B6: 开发中 | C6: CRM-经销商账号 | D6: 产品 | F6: =D6&E6 -> 产品
A7: 6 | B7: 开发中 | C7: CRM-经销商账号 | D7: 销售订单 | E7: 订单查询 | F7: =D7&E7 -> 销售订单订单查询 | H7: 均在“销售订单”同一个界面展示
A8: 7 | B8: 开发中 | C8: CRM-经销商账号 | D8: 销售订单 | E8: 订单进度表查询 | F8: =D8&E8 -> 销售订单订单进度表查询 | H8: 均在“销售订单”同一个界面展示
A9: 8 | B9: 开发中 | C9: CRM-经销商账号 | D9: 销售订单 | E9: 创建常规订单 | F9: =D9&E9 -> 销售订单创建常规订单 | H9: 均在“销售订单”同一个界面展示
A10: 9 | B10: 开发中 | C10: CRM-经销商账号 | D10: 销售订单 | E10: 创建计划订单 | F10: =D10&E10 -> 销售订单创建计划订单 | H10: 均在“销售订单”同一个界面展示
A11: 10 | B11: 开发中 | C11: CRM-经销商账号 | D11: 销售订单 | E11: 创建广告物料订单 | F11: =D11&E11 -> 销售订单创建广告物料订单 | H11: 均在“销售订单”同一个界面展示
A12: 11 | B12: 开发中 | C12: CRM-经销商账号 | D12: 销售订单 | E12: 创建定制订单 | F12: =D12&E12 -> 销售订单创建定制订单 | H12: 均在“销售订单”同一个界面展示
A13: 12 | B13: 开发中 | C13: CRM-经销商账号 | D13: 销售订单 | E13: 创建转卖订单 | F13: =D13&E13 -> 销售订单创建转卖订单 | H13: 均在“销售订单”同一个界面展示
A14: 13 | B14: 开发中 | C14: CRM-经销商账号 | D14: 出口订单 | E14: 创建出口常规订单 | F14: =D14&E14 -> 出口订单创建出口常规订单 | H14: 出口客户才有的菜单，均在“出口订单”同一个界面展示
A15: 14 | B15: 开发中 | C15: CRM-经销商账号 | D15: 出口订单 | E15: 创建出口计划订单 | F15: =D15&E15 -> 出口订单创建出口计划订单 | H15: 出口客户才有的菜单，均在“出口订单”同一个界面展示
A16: 15 | B16: 开发中 | C16: CRM-经销商账号 | D16: 出口订单 | E16: 创建出口定制订单 | F16: =D16&E16 -> 出口订单创建出口定制订单 | H16: 出口客户才有的菜单，均在“出口订单”同一个界面展示
A17: 16 | B17: 开发中 | C17: CRM-经销商账号 | D17: 出口订单 | E17: 创建成品出口退货订单 | F17: =D17&E17 -> 出口订单创建成品出口退货订单 | H17: 出口客户才有的菜单，均在“出口订单”同一个界面展示
A18: 17 | B18: 开发中 | C18: CRM-经销商账号 | D18: 退货订单 | E18: 退货申请单查询 | F18: =D18&E18 -> 退货订单退货申请单查询 | H18: 均在“退货订单”同一个界面展示
... A20: 19 | B20: 开发中 | C20: CRM-经销商账号 | D20: 退货订单 | E20: 创建一件代发退货单 | F20: =D20&E20 -> 退货订单创建一件代发退货单 | H20: 均在“退货订单”同一个界面展示
A21: 20 | B21: 开发中 | C21: CRM-经销商账号 | D21: 经销商维护自选可售产品清单 | F21: =D21&E21 -> 经销商维护自选可售产品清单
A22: 21 | B22: 开发中 | C22: CRM-经销商账号 | D22: 出库单查询 | F22: =D22&E22 -> 出库单查询
A23: 22 | B23: 开发中 | C23: CRM-经销商账号 | D23: 库存查询 | F23: =D23&E23 -> 库存查询
A24: 23 | B24: 开发中 | C24: CRM-经销商账号 | D24: 事业部库存查询 | F24: =D24&E24 -> 事业部库存查询
A25: 24 | B25: 开发中 | C25: CRM-经销商账号 | D25: 折扣政策 | F25: =D25&E25 -> 折扣政策
A26: 25 | B26: 开发中 | C26: CRM-经销商账号 | D26: 对账单 | F26: =D26&E26 -> 对账单 | H26: 旧维度-经销商维度
A27: 26 | B27: 开发中 | C27: CRM-经销商账号 | D27: 发票信息 | F27: =D27&E27 -> 发票信息 | H27: 旧维度-经销商维度
A28: 27 | B28: 开发中 | C28: CRM-经销商账号 | D28: 数据管理 | E28: 退货申请单订单行导入 | F28: =D28&E28 -> 数据管理退货申请单订单行导入 | H28: 通用数据导入，均在“数据管理”同一个界面展示
A29: 28 | B29: 开发中 | C29: CRM-经销商账号 | D29: 数据管理 | E29: 2024销售订单头行导入 | F29: =D29&E29 -> 数据管理2024销售订单头行导入 | H29: 通用数据导入，均在“数据管理”同一个界面展示
A30: 29 | B30: 开发中 | C30: CRM-经销商账号 | D30: 数据管理 | E30: 2024销售订单行导入 | F30: =D30&E30 -> 数据管理2024销售订单行导入 | H30: 通用数据导入，均在“数据管理”同一个界面展示
A31: 30 | B31: 开发中 | C31: CRM-经销商账号 | D31: 收款认领 | F31: =D31&E31 -> 收款认领
A32: 31 | B32: 开发中 | C32: CRM-经销商账号 | D32: 审核未发运查询 | F32: =D32&E32 -> 审核未发运查询
A33: 32 | B33: 开发中 | C33: CRM-经销商账号 | D33: 月度库存上传 | F33: =D33&E33 -> 月度库存上传
A34: 33 | B34: 开发中 | C34: CRM-经销商账号 | D34: 经销商子账号管理 | F34: =D34&E34 -> 经销商子账号管理
A35: 34 | B35: 开发中 | C35: CRM-法人账号 | D35: 我的导出（异步） | F35: =D35&E35 -> 我的导出（异步）
A36: 35 | B36: 开发中 | C36: CRM-法人账号 | D36: 法人客户 | F36: =D36&E36 -> 法人客户
A37: 36 | B37: 开发中 | C37: CRM-法人账号 | D37: 法人对账单 | F37: =D37&E37 -> 法人对账单 | H37: 新版本
A38: 37 | B38: 开发中 | C38: CRM-法人账号 | D38: 对账单 | F38: =D38&E38 -> 对账单 | H38: 历史版本
A39: 38 | B39: 开发中 | C39: CRM-法人账号 | D39: 经销商账户明细查询 | F39: =D39&E39 -> 经销商账户明细查询
A40: 39 | B40: 开发中 | C40: CRM-法人账号 | D40: 待兑现折扣折让对账单 | F40: =D40&E40 -> 待兑现折扣折让对账单
A41: 40 | B41: 开发中 | C41: CRM-法人账号 | D41: 额度内市场推广费用对账单 | F41: =D41&E41 -> 额度内市场推广费用对账单
A42: 41 | B42: 开发中 | C42: CRM-法人账号 | D42: 客户金税发票号码查询 | F42: =D42&E42 -> 客户金税发票号码查询
A43: 42 | B43: 开发中 | C43: CRM-经销商账号 | D43: 销售订单 | E43: 订单行优先发货顺序维护 | F43: =D43&E43 -> 销售订单订单行优先发货顺序维护 | H43: 新功能，现在CRM-DMS还在开发当中
A44: 43 | B44: 开发中 | C44: CRM-经销商账号 | D44: 占用定金明细报表 | F44: =D44&E44 -> 占用定金明细报表 | H44: 新功能，现在CRM-DMS还在开发当中
A45: 44 | B45: 未来计划 | C45: CRM-内部用户 | D45: 经销商 | E45: 经销商360 | H45: 1、基地、可自行维护发运部门、收货地址，不涉及对接OA审批。 2、展厅业务员可自行维护收货地址，不涉及对接OA审批。
A46: 45 | B46: 未来计划 | C46: CRM-内部用户 | D46: 经销商 | E46: 经销商+渠道设置定金比例 | H46: 一般为物流部调度维护。
A47: 46 | B47: 未来计划 | C47: CRM-内部用户 | D47: 经销商 | E47: 经销商-基础信息维护 | H47: 集团财务、基地财务，有审核权限。
A48: 47 | B48: 未来计划 | C48: CRM-内部用户 | D48: 经销商 | E48: 经销商-客户合同维护 | H48: 总经办焦冉冉才有审核权限。
A49: 48 | B49: 未来计划 | C49: CRM-内部用户 | D49: 经销商 | E49: 经销商-开票单位维护 | H49: 集团财务、基地财务，有审核权限。
A50: 49 | B50: 未来计划 | C50: CRM-内部用户 | D50: 经销商 | E50: 全年折扣管理 | H50: 集团财务查询、维护。
A51: 50 | B51: 未来计划 | C51: CRM-内部用户 | D51: 经销商 | E51: 经销商-不可异动设置 | H51: 管理员操作
A52: 51 | B52: 未来计划 | C52: CRM-内部用户 | D52: 经销商 | E52: 经销商-含运费标识维护
A53: 52 | B53: 未来计划 | C53: CRM-内部用户 | D53: 经销商 | E53: 经销商-意向客户 | H53: 海外销售业务使用
A54: 53 | B54: 未来计划 | C54: CRM-内部用户 | D54: 发运部门维护 | E54: 发运部门申请单 | H54: 各销售业务员进行申请提交OA审批
A55: 54 | B55: 未来计划 | C55: CRM-内部用户 | D55: 发运部门维护 | E55: 发运部门查询
A56: 55 | B56: 未来计划 | C56: CRM-内部用户 | D56: 法人客户 | E56: 法人信息变更申请 | H56: 一般为运营部、计划物流中心新建、提交OA审批
A57: 56 | B57: 未来计划 | C57: CRM-内部用户 | D57: 法人客户 | E57: 法人客户同控信息 | H57: 集团财务
A58: 57 | B58: 未来计划 | C58: CRM-内部用户 | D58: 产品 | E58: 产品列表
A59: 58 | B59: 未来计划 | C59: CRM-内部用户 | D59: 产品 | E59: 价目表 | H59: 产品部一般有申请导出权限。
A60: 59 | B60: 未来计划 | C60: CRM-内部用户 | D60: 产品 | E60: 配件产品维护
A61: 60 | B61: 未来计划 | C61: CRM-内部用户 | D61: 产品 | E61: 价目表申请单 | H61: 一般为产品部进行定价申请
A62: 61 | B62: 未来计划 | C62: CRM-内部用户 | D62: 产品 | E62: 产品淘汰申请 | H62: 废弃功能
A63: 62 | B63: 未来计划 | C63: CRM-内部用户 | D63: 产品 | E63: 包销产品维护 | H63: 废弃功能
A64: 63 | B64: 未来计划 | C64: CRM-内部用户 | D64: 产品 | E64: 浴室柜套装关联 | H64: 废弃功能
A65: 64 | B65: 未来计划 | C65: CRM-内部用户 | D65: 产品 | E65: 组合套装关联 | H65: 产品部使用的功能
A66: 65 | B66: 未来计划 | C66: CRM-内部用户 | D66: 产品 | E66: 产品订金比例设置 | H66: 一般为物流部调度维护。
A67: 66 | B67: 未来计划 | C67: CRM-内部用户 | D67: 产品 | E67: 责任制内结价定价基础参数配置 | H67: 财务庞少斌维护
A68: 67 | B68: 未来计划 | C68: CRM-内部用户 | D68: 产品 | E68: 责任制内结价定价瓷砖参数配置 | H68: 财务庞少斌维护
A69: 68 | B69: 未来计划 | C69: CRM-内部用户 | D69: 产品 | E69: 全国生产起订量定义 | H69: 一般为物流部调度维护。
A70: 69 | B70: 未来计划 | C70: CRM-内部用户 | D70: 产品 | E70: 生产周期天数定义 | H70: 一般为物流部调度维护。
A71: 70 | B71: 未来计划 | C71: CRM-内部用户 | D71: 产品 | E71: 事业部公共产品清单维护 | H71: 一般为物流部调度维护。
A72: 71 | B72: 未来计划 | C72: CRM-内部用户 | D72: 产品 | E72: 事业部自选产品清单维护 | H72: 一般为物流部调度维护。
... A81: 80 | B81: 未来计划 | C81: CRM-内部用户 | D81: 订单 | E81: 创建配件订单 | H81: 非客服公司备件业务，才涉及创建，例如龙甫外委订单
A82: 81 | B82: 未来计划 | C82: CRM-内部用户 | D82: 订单 | E82: 创建广告物料
A83: 82 | B83: 未来计划 | C83: CRM-内部用户 | D83: 订单 | E83: 创建废料订单
A84: 83 | B84: 未来计划 | C84: CRM-内部用户 | D84: 订单 | E84: 创建出口退货订单
A85: 84 | B85: 未来计划 | C85: CRM-内部用户 | D85: 订单 | E85: 创建成品退货订单 | H85: 非售后退货、自营退货才是CRM新建，其余在新客服系统创建
A86: 85 | B86: 未来计划 | C86: CRM-内部用户 | D86: 订单 | E86: 创建配件退货订单
A87: 86 | B87: 未来计划 | C87: CRM-内部用户 | D87: 订单 | E87: 创建废料退货订单
A88: 87 | B88: 未来计划 | C88: CRM-内部用户 | D88: 订单 | E88: 造易排错 | H88: 管理员操作
A89: 88 | B89: 未来计划 | C89: CRM-内部用户 | D89: 订单 | E89: 创建转卖退货订单
A90: 89 | B90: 未来计划 | C90: CRM-内部用户 | D90: 订单 | E90: 合并提交 | H90: 工程定制订单可用
A91: 90 | B91: 未来计划 | C91: CRM-内部用户 | D91: 订单 | E91: 订单查询（异常单处理） | H91: 管理员操作
A92: 91 | B92: 未来计划 | C92: CRM-内部用户 | D92: 订单 | E92: 订单进度表 | H92: 仅针对定制订单
A93: 92 | B93: 未来计划 | C93: CRM-内部用户 | D93: 订单 | E93: 定制订单批量抛OA | H93: 仅针对定制订单
A94: 93 | B94: 未来计划 | C94: CRM-内部用户 | D94: 订单 | E94: 定制订单批量审核 | H94: 仅针对定制订单
A95: 94 | B95: 未来计划 | C95: CRM-内部用户 | D95: 订单 | E95: 定制卫浴小模块批量审核 | H95: 废弃功能
A96: 95 | B96: 未来计划 | C96: CRM-内部用户 | D96: 订单 | E96: 配件订单批量审核 | H96: 废弃功能
A97: 96 | B97: 未来计划 | C97: CRM-内部用户 | D97: 订单 | E97: 软装（广告物料申请单）批量审核 | H97: 软装经理黄忠平使用
A98: 97 | B98: 未来计划 | C98: CRM-内部用户 | D98: 订单 | E98: 订单重推ERP记录 | H98: 管理员操作
A99: 98 | B99: 未来计划 | C99: CRM-内部用户 | D99: 出库单 | E99: 退货明细查询 | H99: 按所属安全性控制范围
A100: 99 | B100: 未来计划 | C100: CRM-内部用户 | D100: 库存查询 | E100: 库存显示配置 | H100: 管理员操作
A101: 100 | B101: 未来计划 | C101: CRM-内部用户 | D101: 库存查询 | E101: 一件代发库存查询 | H101: 管理员操作
A102: 101 | B102: 未来计划 | C102: CRM-内部用户 | D102: 条码查询 | E102: 日志查询
A103: 102 | B103: 未来计划 | C103: CRM-内部用户 | D103: 工程管理 | E103: 战略工程 | H103: 历史功能，EPMS上线后已没维护
A104: 103 | B104: 未来计划 | C104: CRM-内部用户 | D104: 工程管理 | E104: 单体工程CRM | H104: 历史功能，EPMS上线后已没维护
A105: 104 | B105: 未来计划 | C105: CRM-内部用户 | D105: 工程管理 | E105: 合同审核 | H105: 历史功能，EPMS上线后已没维护
A106: 105 | B106: 未来计划 | C106: CRM-内部用户 | D106: 工程管理 | E106: 单体工程 | H106: 历史功能，EPMS上线后已没维护
A107: 106 | B107: 未来计划 | C107: CRM-内部用户 | D107: 对账单 | E107: 内部明细 | H107: 历史功能，旧对账维度数据
A108: 107 | B108: 未来计划 | C108: CRM-内部用户 | D108: 对账单 | E108: 外部明细 | H108: 历史功能，旧对账维度数据
A109: 108 | B109: 未来计划 | C109: CRM-内部用户 | D109: 对账单 | E109: 法人对账单 | H109: 新维度对账数据，在用
...

Sheet AE计划菜单
A1: 系统 | B1: 一级菜单 | C1: 二级菜单 | D1: 三级菜单 | G1: MENUNAME | H1: MENUID | I1: MENUNAME
A2: AMCS | B2: 营销中台 | C2: 基础资料 | D2: 基础资料 | G2: 合同产品变更 | H2: 12036157 | I2: 合同产品变更
A3: AMCS | B3: 营销中台 | C3: 基础资料 | D3: 经销商档案 | G3: 库存查询 | H3: 12036152 | I3: 库存查询
A4: AMCS | B4: 营销中台 | C4: 基础资料 | D4: 分销商档案 | G4: 客户资料 | H4: 12036115 | I4: 客户资料
A5: AMCS | B5: 营销中台 | C5: 基础资料 | D5: 法人客户档案 | G5: 自营工程合同 | H5: 12035907 | I5: 自营工程合同
A6: AMCS | B6: 营销中台 | C6: 基础资料 | D6: 交易公司 | G6: 自营工程签收 | H6: 12035854 | I6: 自营工程签收
A7: AMCS | B7: 营销中台 | C7: 基础资料 | D7: 供应商档案 | G7: 工程出库单 | H7: 12035853 | I7: 工程出库单
A8: AMCS | B8: 营销中台 | C8: 基础资料 | D8: 事业部设置 | G8: 工程要货订单 | H8: 12035851 | I8: 工程要货订单
A9: AMCS | B9: 营销中台 | C9: 基础资料 | D9: 行政区域 | G9: 工程折扣单 | H9: 12035849 | I9: 工程折扣单
A10: AMCS | B10: 营销中台 | C10: 基础资料 | D10: 合同类型与销售渠道关联关系设置 | G10: 项目合同变更 | H10: 12035845 | I10: 项目合同变更
A11: AMCS | B11: 营销中台 | C11: 门店管理 | D11: 广告费余额查询 | G11: 经销商工程合同 | H11: 12035844 | I11: 经销商工程合同
A12: AMCS | B12: 营销中台 | C12: 门店管理 | D12: 广告费余额调整 | G12: 项目进度更新 | H12: 12035834 | I12: 项目进度更新
A13: AMCS | B13: 营销中台 | C13: 门店管理 | D13: 广告费调整申请单 | G13: 折扣延期申请 | H13: 12036166 | I13: 折扣延期申请
... A180: EPMS | B180: 家装项目 | C180: 报表中心 | D180: 家装核销发票上传明细报表 | G180: 说明书分类 | H180: 12036367 | I180: 说明书分类
A181: 基础资料 | B181: 12035817 | C181: 不用的主菜单 | G181: 事业部设置 | H181: 12036150 | I181: 事业部设置
A182: 商机报备 | B182: 12035832 | C182: 不用的主菜单 | G182: 工程项目安装调试质量报表 | H182: 12036402 | I182: 工程项目安装调试质量报表
A183: 项目合同 | B183: 12035842 | C183: 不用的主菜单 | G183: 销售区域 | H183: 12035824 | I183: 销售区域
A184: 项目交付 | B184: 12035848 | C184: 不用的主菜单 | G184: 工程折扣政策申请 | H184: 12036490 | I184: 工程折扣政策申请
A185: 项目应付 | B185: 12035856 | C185: 不用的主菜单 | G185: 合同保证金标准设置 | H185: 12036500 | I185: 合同保证金标准设置
A186: 项目应收 | B186: 12035857 | C186: 不用的主菜单 | G186: 认缴概况 | H186: 12036499 | I186: 认缴概况
A187: 进度报表 | B187: 12035874 | C187: 不用的主菜单 | G187: 保证金减免申请 | H187: 12036498 | I187: 保证金减免申请
A188: 基础设置 | B188: 12036135 | C188: 不用的主菜单 | G188: 工程折扣政策失效 | H188: 12036491 | I188: 工程折扣政策失效
A189: 信息查询 | B189: 12036151 | C189: 不用的主菜单 | G189: 店面额度内兑现余额表 | H189: 12036488 | I189: 店面额度内兑现余额表
A190: 报表查询 | B190: 12036170 | C190: 不用的主菜单
A191: 紧急要货 | B191: 12036176 | C191: 不用的主菜单
A192: 家装交付 | B192: 12036218 | C192: 不用的主菜单
A193: 信息查询 | B193: 12036219 | C193: 不用的主菜单
A194: 报表查询 | B194: 12036220 | C194: 不用的主菜单
A195: 家装商机 | B195: 12036247 | C195: 不用的主菜单
A196: 家装合同 | B196: 12036260 | C196: 不用的主菜单
A197: 产品资料/图册 | B197: 12036266 | C197: 不用的主菜单
A198: 产品管理 | B198: 12036267 | C198: 不用的主菜单
A199: 销售合同 | B199: 12036275 | C199: 不用的主菜单
A200: 基础资料 | B200: 12036280 | C200: 不用的主菜单
A201: 门店档案 | B201: 12036301 | C201: 不用的主菜单
... A217: 真实性核销 | B217: 12036477 | C217: 不用的主菜单

Sheet 权限规则

Sheet 副本
N1: SIT权限检查（ 外部：1代表权限已配好，反之则为2。 内部：3代表、权限已配好，反之则为4） | T1: 查看当前账号关联的经销商（单个）数据 | AE1: 查看当前登录事业部的所有数据 | AN1: 以事业部维度，查看个人创建或个人关联经销商数据 | AR1: 以事业部维度，查看个人创建或个人关联经销商或当前部门下属所管辖经销商数据 | AT1: 查看当前登录事业部所有的数据 | BL1: MBO业务
A2: 菜单编码（唯一） | B2: 一级菜单 | C2: 二级菜单 | D2: 三级菜单 | E2: 经销商可阅 | F2: 内部可阅/废弃 | G2: 涉及系统 | H2: 需业务测试 | I2: AE_MENUID | J2: 备注 | K2: 原菜单路径1 | L2: 原菜单路径2 | M2: 原菜单路径3 | N2: 配置优先级 | O2: 技术配置 | P2: 汉得复核 | Q2: 箭牌复核sit | R2: 默认菜单按钮权限 | S2: █经销商权限█ | T2: 经销商 主账号 | U2: 法人账号 | V2: 经销商 负责人 | W2: 经销商 采购 | X2: 经销商 仓管 | Y2: 经销商 财务 | Z2: 经销商工程报备 | AA2: 经销商家装报备 | AB2: 经销商产品专员 | AC2: 出口经销商 | AD2: 电子合同签章 | AE2: 价格查询 | AF2: 工厂库存查询 | AG2: 工程报备专员 | AH2: 家装报备专员 | AI2: 报备查询 | AJ2: 工程合同专员 | AK2: 家装合同专员 | AL2: 运营管理 | AM2: █报备、合同、运营默认按钮权限█ | AN2: 战略工程项目管理 | AO2: 工程项目管理 | AP2: 家装项目管理 | AQ2: 区域销售代表 | AR2: 大区管理 | AS2: █项目、区域销售默认权限█ | AT2: 发货专员 | AU2: 调度专员 | AV2: 计划物流 | AW2: █发货、调度、物流默认权限█ | AX2: 销售财务 | AY2: █财务默认权限█ | AZ2: BI人员查看 | BA2: 自营工程签收 | BB2: 发票作废与取消核销 | BC2: 真实性核销审核 | BD2: 产品维护 | BE2: 产品推广等级维护 | BF2: 产品SM状态变更 | BG2: 售后产品SM状态变更 | BH2: 产品说明书维护 | BI2: 软装经理 | BJ2: 软装总监 | BK2: █产品维护权限█ | BL2: 培训师 | BM2: 活动策划师 | BN2: 设计师 | BO2: 培训管理员 | BP2: 活动策划管理员 | BQ2: 设计师管理员 | BR2: 集团合同管理员 | BS2: 问题反馈处理回复 | BT2: 菜单使用频率
A3: 1 | B3: 基础资料 | C3: 客户资料 | D3: 经销商档案 | E3: 是 | F3: 是 | G3: CRM/AE/MBO | H3: 是 | I3: 12036281，12036115 | J3: （查询+新建地址） | N3: 3 | O3: 待确认 | S3: 编辑 | T3: √ | V3: √ | Y3: √ | AL3: √ | AQ3: √ | AT3: √ | AV3: √ | AW3: 编辑 | AX3: √ | AY3: 编辑,导出 | BI3: √ | BJ3: √ | BT3: =COUNTIF(T3:BS3,"=√") -> 10
A4: 2 | B4: 基础资料 | C4: 客户资料 | D4: 法人客户档案 | E4: 法人 | F4: 是 | G4: CRM/AE/MBO | H4: 是 | I4: 12036284 | K4: AMCS-基础资料-法人客户档案 | L4: AMCS-基础资料-交易公司 | N4: 3 | T4: 见法人对账 | U4: √ | Y4: √ | AL4: √ | AQ4: √ | AT4: √ | AV4: √ | AW4: 编辑 | AX4: √ | AY4: 导出 | BI4: √ | BT4: =COUNTIF(T4:BS4,"=√") -> 8
A5: 3 | B5: 基础资料 | C5: 客户资料 | D5: 供应商档案 | F5: 是 | G5: AE | H5: 是 | I5: 12036282，12035823 | R5: 除导出外不限 | AJ5: √ | AK5: √ | AL5: √ | AM5: 全部数据 | AN5: √ | AO5: √ | AQ5: √ | AS5: 编辑,全部数据 | AX5: √ | AY5: 导出,全部数据 | BT5: =COUNTIF(T5:BS5,"=√") -> 7
A6: 4 | B6: 基础资料 | C6: 客户资料 | D6: 分销商档案 | E6: 是 | F6: 是 | G6: AE | H6: 是 | I6: 12036349 | N6: 3 | O6: 1、3 | R6: 除导出外不限 | S6: 编辑 | T6: √ | V6: √ | Y6: √ | AL6: √ | AQ6: √ | AS6: 编辑 | AX6: √ | AY6: 导出 | BT6: =COUNTIF(T6:BS6,"=√") -> 6
A7: 231 | B7: 基础资料 | C7: 订单设置 | D7: 产品线关联设置 | F7: IT | G7: CRM/AE | I7: 12036136 | R7: 不限 | BT7: =COUNTIF(T7:BS7,"=√") -> 0
A8: 232 | B8: 基础资料 | C8: 订单设置 | D8: 产品渠道设置 | F8: IT | G8: CRM/AE | I8: 12036141 | R8: 不限 | BT8: =COUNTIF(T8:BS8,"=√") -> 0
A9: 233 | B9: 基础资料 | C9: 订单设置 | D9: 业务渠道设置 | F9: IT | G9: CRM/AE | I9: 12036145 | R9: 不限 | BT9: =COUNTIF(T9:BS9,"=√") -> 0
A10: 234 | B10: 基础资料 | C10: 订单设置 | D10: 产品线维护 | F10: IT | G10: CRM/AE | I10: 12036146 | R10: 不限 | BT10: =COUNTIF(T10:BS10,"=√") -> 0
A11: 235 | B11: 基础资料 | C11: 常规设置 | D11: 行政区域 | F11: IT | G11: CRM/AE/MBO | I11: 12036290，12036160 | R11: 不限 | AG11: √ | AH11: √ | AJ11: √ | AK11: √ | AL11: √ | AM11: 全部数据 | AN11: √ | AO11: √ | AP11: √ | AQ11: √ | AS11: 全部数据 | AX11: √ | AY11: 全部数据 | BT11: =COUNTIF(T11:BS11,"=√") -> 10
A12: 236 | B12: 基础资料 | C12: 常规设置 | D12: 事业部设置 | F12: IT | G12: CRM/AE | I12: 12036287，12036150 | R12: 不限 | BT12: =COUNTIF(T12:BS12,"=√") -> 0
A13: 237 | B13: 基础资料 | C13: 常规设置 | D13: 合同类型与销售渠道关联关系设置 | F13: IT | G13: AE | I13: 12036482 | R13: 不限 | BT13: =COUNTIF(T13:BS13,"=√") -> 0
A14: 238 | B14: 基础资料 | C14: 常规设置 | D14: 项目进度定义 | F14: IT | G14: AE | I14: 12035897 | R14: 不限 | BT14: =COUNTIF(T14:BS14,"=√") -> 0
A15: 5 | B15: 基础资料 | C15: 常规设置 | D15: 行政销售区域对照列表 | F15: 是 | G15: AE | H15: 是 | I15: 12036463 | R15: 不限 | AG15: √ | AJ15: √ | AL15: √ | AM15: 编辑,导出 | AX15: √ | BT15: =COUNTIF(T15:BS15,"=√") -> 4
A16: 6 | B16: 基础资料 | C16: 常规设置 | D16: 单据审批人对照表 | G16: AE | H16: 是 | I16: 12036464 | R16: 不限 | AG16: √ | AJ16: √ | AL16: √ | AM16: 编辑,导出 | AX16: √ | BT16: =COUNTIF(T16:BS16,"=√") -> 4
A17: 240 | B17: 基础资料 | C17: 常规设置 | D17: 数据权限设置 | F17: IT | G17: AE | I17: 12036163 | R17: 不限 | BT17: =COUNTIF(T17:BS17,"=√") -> 0
A18: 241 | B18: 基础资料 | C18: 常规设置 | D18: 经销商配置 | F18: IT | G18: AE | I18: 12036389 | R18: 不限 | BT18: =COUNTIF(T18:BS18,"=√") -> 0
A19: 7 | B19: 基础资料 | C19: 常规设置 | D19: 节假日维护（无） | F19: 是 | G19: AE | H19: 是 | I19: 12036492 | R19: 不限 | AG19: √ | AL19: √ | AM19: 编辑,导出,全部数据 | AX19: √ | AY19: 全部数据 | BT19: =COUNTIF(T19:BS19,"=√") -> 3
A20: 8 | B20: 产品中心 | C20: 产品资料 | D20: 产品列表 | E20: 是 | F20: 是 | G20: CRM/AE | H20: 是 | I20: 12036297 | N20: 3 | S20: 导出 | T20: √ | V20: √ | W20: √ | Y20: √ | AB20: √ | AG20: √ | AH20: √ | AJ20: √ | AK20: √ | AL20: √ | AN20: √ | AO20: √ | AP20: √ | AQ20: √ | AR20: √ | AS20: 关联事业部的全部 | AT20: √ | AU20: √ | AV20: √ | AW20: 导出 | AX20: √ | BD20: √ | BF20: √ | BG20: √ | BT20: =COUNTIF(T20:BS20,"=√") -> 22
A21: 9 | B21: 产品中心 | C21: 产品资料 | D21: 产品变更列表 | F21: 是 | G21: CRM/AE | H21: 是 | J21: 包含上下架、推广资料、图册与附件、关联产品 | AU21: √ | AV21: √ | BD21: √ | BT21: =COUNTIF(T21:BS21,"=√") -> 3
A22: 10 | B22: 产品中心 | C22: 产品资料 | D22: 产品推广等级字段要求配置 | F22: 是 | G22: CRM/AE | H22: 是 | BE22: √ | BT22: =COUNTIF(T22:BS22,"=√") -> 1
A23: 11 | B23: 产品中心 | C23: 产品资料 | D23: 产品推广等级维护 | F23: 是 | G23: CRM/AE | H23: 是 | BE23: √ | BK23: 编辑,导出 | BT23: =COUNTIF(T23:BS23,"=√") -> 1
A24: 12 | B24: 产品中心 | C24: 产品资料 | D24: 产品图册维护（废弃原AE功能） | F24: 是 | G24: CRM/AE | H24: 是 | I24: 12036299 | K24: AE产品图册上传 | L24: AE产品图册 | BD24: √ | BT24: =COUNTIF(T24:BS24,"=√") -> 1
A25: 13 | B25: 产品中心 | C25: 产品资料 | D25: 产品SM状态变更申请 | F25: 是 | G25: AE | H25: 是 | I25: 12036305 | R25: 不限 | BF25: √ | BG25: √ | BT25: =COUNTIF(T25:BS25,"=√") -> 2
A26: 14 | B26: 产品中心 | C26: 说明书 | D26: 产品说明书 | F26: 是 | G26: AE | H26: 是 | I26: 12036368 | R26: 不限 | BH26: √ | BT26: =COUNTIF(T26:BS26,"=√") -> 1
A27: 15 | B27: 产品中心 | C27: 说明书 | D27: 说明书分类 | F27: 是 | G27: AE | H27: 是 | I27: 12036367 | R27: 除导出外不限 | BH27: √ | BT27: =COUNTIF(T27:BS27,"=√") -> 1
A28: 16 | B28: 产品中心 | C28: 说明书 | D28: 说明书查阅数据 | F28: 是 | G28: AE | I28: 12036369 | R28: 除导出外不限 | BH28: √ | BT28: =COUNTIF(T28:BS28,"=√") -> 1
A29: 17 | B29: 产品中心 | C29: 说明书 | D29: 说明书关联产品 | F29: 是 | G29: AE | I29: 12036373 | R29: 除导出外不限 | BH29: √ | BT29: =COUNTIF(T29:BS29,"=√") -> 1
A30: 242 | B30: 产品中心 | C30: 产品设置 | D30: (未来) | F30: IT | G30: CRM | K30: 经销商维护自选可售产品清单 | BT30: =COUNTIF(T30:BS30,"=√") -> 0
A31: 18 | B31: 产品中心 | C31: 价目表 | D31: 价目表查询 | E31: 是 | F31: 是 | G31: CRM/AE | H31: 是 | I31: 12036465 | J31: 12036466 | K31: 价目表 | N31: 3 | T31: √ | V31: √ | W31: √ | Y31: √ | AE31: √ | AL31: √ | AN31: √ | AO31: √ | AP31: √ | AQ31: √ | AR31: √ | AS31: 关联事业部的全部数据 | AT31: √ | AU31: √ | AV31: √ | AX31: √ | AY31: 导出 | BT31: =COUNTIF(T31:BS31,"=√") -> 15
A32: 19 | B32: 产品中心 | C32: 库存 | D32: 库存查询 | E32: 是 | F32: 是 | G32: CRM/AE | H32: 是 | I32: 12036152 | J32: 经销商/内部， | K32: 库存查询 | N32: 3 | T32: √ | V32: √ | W32: √ | X32: √ | Y32: √ | AF32: √ | AL32: √ | AN32: √ | AO32: √ | AP32: √ | AQ32: √ | AR32: √ | AS32: 关联事业部的全部数据 | AT32: √ | AU32: √ | AV32: √ | AX32: √ | BT32: =COUNTIF(T32:BS32,"=√") -> 16
A33: 20 | B33: 产品中心 | C33: 库存 | D33: 库存查询 | F33: 是，未来 | G33: CRM | J33: (内部-未来) | AO33: √ | AP33: √ | AQ33: √ | AS33: 关联事业部的全部数据 | BT33: =COUNTIF(T33:BS33,"=√") -> 3
A34: 21 | B34: 产品中心 | C34: 库存 | D34: 事业部库存查询 | E34: 是 | F34: 是 | G34: CRM | J34: （经销商)责任制 | K34: 事业部库存查询 | T34: √ | V34: √ | W34: √ | X34: √ | Y34: √ | BI34: √ | BJ34: √ | BT34: =COUNTIF(T34:BS34,"=√") -> 7
A35: 22 | B35: 门店管理 | C35: 门店档案 | D35: 新建门店申请 | E35: 是 | F35: 是 | G35: AE | H35: 是 | I35: 12036309 | N35: 3 | O35: 1、3 | R35: 除导出外不限 | S35: 编辑 | T35: √ | V35: √ | Y35: √ | AC35: √ | AL35: √ | AQ35: √ | AS35: 编辑 | AX35: √ | AY35: 导出 | BT35: =COUNTIF(T35:BS35,"=√") -> 7
A36: 23 | B36: 门店管理 | C36: 门店档案 | D36: 门店档案 | E36: 是 | F36: 是 | G36: AE | H36: 是 | I36: 12036311 | N36: 3 | O36: 1、3 | T36: √ | V36: √ | Y36: √ | AC36: √ | AL36: √ | AM36: 导出 | AQ36: √ | AS36: 导出 | AX36: √ | AY36: 导出 | AZ36: √ | BT36: =COUNTIF(T36:BS36,"=√") -> 8
A37: 24 | B37: 门店管理 | C37: 门店档案 | D37: 门店变更申请 | E37: 是 | F37: 是 | G37: AE | H37: 是 | I37: 12036312 | N37: 3 | O37: 1、3 | R37: 除导出外不限 | S37: 编辑 | T37: √ | V37: √ | Y37: √ | AC37: √ | AL37: √ | AQ37: √ | AS37: 编辑 | AX37: √ | AY37: 导出 | BT37: =COUNTIF(T37:BS37,"=√") -> 7
A38: 25 | B38: 门店管理 | C38: 门店设置 | D38: 门店照片设置 | G38: AE | I38: 12036313 | AL38: √ | AM38: 编辑,导出 | AQ38: √ | AS38: 关联事业部的全部数据 | AX38: √ | AY38: 导出 | BT38: =COUNTIF(T38:BS38,"=√") -> 3
A39: 26 | B39: 门店管理 | C39: 门店设置 | D39: 门店验收信息设置 | G39: AE | I39: 12036421 | AL39: √ | AM39: 编辑,导出 | AQ39: √ | AS39: 关联事业部的全部数据 | AX39: √ | AY39: 导出 | BT39: =COUNTIF(T39:BS39,"=√") -> 3
A40: 27 | B40: 门店管理 | C40: 门店设置 | D40: 门店装修标准 | F40: 是 | G40: AE | H40: 是 | I40: 12036422 | AL40: √ | AM40: 编辑,导出 | AQ40: √ | AS40: 关联事业部的全部数据 | AX40: √ | AY40: 导出 | BT40: =COUNTIF(T40:BS40,"=√") -> 3
A41: 28 | B41: 门店管理 | C41: 门店档案 | D41: 门头展板报销标准 | F41: 是 | G41: AE | H41: 是 | I41: 12036508 | AL41: √ | AM41: 编辑,导出 | AQ41: √ | AS41: 关联事业部的全部数据 | AX41: √ | AY41: 导出 | BT41: =COUNTIF(T41:BS41,"=√") -> 3
A42: 29 | B42: 门店管理 | C42: 门店设置 | D42: 经销商额度外限额 | G42: AE | H42: 是 | I42: 12036509 | AL42: √ | AM42: 编辑,导出 | AQ42: √ | AS42: 关联事业部的全部数据 | AX42: √ | AY42: 导出 | BT42: =COUNTIF(T42:BS42,"=√") -> 3
A43: 30 | B43: 门店管理 | C43: 门店装修 | D43: 门店装修申请与进度更新 | E43: 是 | F43: 是 | G43: AE | H43: 是 | I43: 12036417 | N43: 2 | O43: 1、3 | R43: 查看流程,打印 | S43: 编辑,作废,重新生成 | T43: √ | V43: √ | Y43: √ | AL43: √ | AQ43: √ | AX43: √ | AY43: 导出 | AZ43: √ | BI43: √ | BJ43: √ | BT43: =COUNTIF(T43:BS43,"=√") -> 9
A44: 31 | B44: 门店管理 | C44: 门店装修 | D44: 门店验收与报销单报表 | E44: 是 | F44: 是 | G44: AE | H44: 是 | I44: 12036454 | N44: 2 | O44: 1、3 | R44: 查看流程,打印 | S44: 作废 | T44: √ | V44: √ | Y44: √ | AL44: √ | AQ44: √ | AS44: 盖章申请 | AX44: √ | AY44: 导出 | AZ44: √ | BI44: √ | BJ44: √ | BR44: √ | BT44: =COUNTIF(T44:BS44,"=√") -> 10
A45: 32 | B45: 门店管理 | C45: 门店装修 | D45: 门店装修额内兑现 | E45: 是 | F45: 是 | G45: AE | H45: 是 | I45: 12036434 | N45: 3 | O45: 1、3 | T45: √ | V45: √ | Y45: √ | AL45: √ | AQ45: √ | AX45: √ | AY45: 导出 | AZ45: √ | BT45: =COUNTIF(T45:BS45,"=√") -> 7
A46: 33 | B46: 门店管理 | C46: 门店装修 | D46: 额度内兑现批量复核 | F46: 财务 | G46: AE | H46: 是 | I46: 12036441 | R46: 不限 | AX46: √ | AY46: 导出 | AZ46: √ | BT46: =COUNTIF(T46:BS46,"=√") -> 2
A47: 34 | B47: 门店管理 | C47: 门店装修 | D47: 门店装修额度外兑现 | E47: 是 | F47: 是 | G47: AE | H47: 是 | I47: 12036419 | N47: 2 | O47: 1、3 | R47: 查看流程 | S47: 编辑 | T47: √ | V47: √ | Y47: √ | AL47: √ | AQ47: √ | AX47: √ | AY47: 导出 | AZ47: √ | BR47: √ | BT47: =COUNTIF(T47:BS47,"=√") -> 8
A48: 35 | B48: 门店管理 | C48: 门店装修 | D48: 门店装修申请变更 | E48: 是 | F48: 是 | G48: AE | H48: 是 | I48: 12036440 | N48: 2 | O48: 1、3 | R48: 查看流程,打印 | S48: 编辑,作废 | T48: √ | V48: √ | Y48: √ | AL48: √ | AQ48: √ | AX48: √ | AY48: 导出 | AZ48: √ | BT48: =COUNTIF(T48:BS48,"=√") -> 7
A49: 36 | B49: 门店管理 | C49: 门店装修 | D49: 门店装修申请关闭 | E49: 是 | F49: 是 | G49: AE | H49: 是 | I49: 12036420 | N49: 5 | R49: 查看流程 | S49: 编辑 | T49: √ | V49: √ | Y49: √ | AL49: √ | AQ49: √ | AS49: 编辑 | AX49: √ | AY49: 导出 | AZ49: √ | BT49: =COUNTIF(T49:BS49,"=√") -> 7
A50: 37 | B50: 门店管理 | C50: 门店装修 | D50: 门头展板报销申请单 | E50: 是 | F50: 是 | G50: AE | H50: 是 | I50: 12036510 | N50: 2 | O50: 低码：待迁移到sit | R50: 查看流程,打印 | S50: 编辑 | T50: √ | V50: √ | Y50: √ | AL50: √ | AM50: 导出 | AQ50: √ | AS50: 编辑,盖章申请 | AX50: √ | AY50: 导出 | BR50: √ | BT50: =COUNTIF(T50:BS50,"=√") -> 7
A51: 38 | B51: 门店管理 | C51: 门店装修 | D51: 门头展板兑现 | E51: 是 | F51: 是 | G51: AE | H51: 是 | I51: 12036511 | N51: 2 | O51: 1、3 | R51: 查看流程,打印 | S51: 编辑 | T51: √ | V51: √ | Y51: √ | AL51: √ | AM51: 导出 | AQ51: √ | AS51: 编辑 | AX51: √ | AY51: 导出 | BT51: =COUNTIF(T51:BS51,"=√") -> 6
A52: 39 | B52: 门店管理 | C52: 广告投放 | D52: 广告投放申请 | E52: 是 | F52: 是 | G52: AE | H52: 是 | I52: 12036351 | J52: 额度内外业务合并 | K52: 广告投放申请 | L52: 额度外广告投放申请 | N52: 2 | O52: 1、3 | R52: 除导出外不限 | S52: 编辑 | T52: √ | V52: √ | Y52: √ | AL52: √ | AM52: 编辑,导出 | AQ52: √ | AS52: 编辑 | AX52: √ | AY52: 导出 | AZ52: √ | BT52: =COUNTIF(T52:BS52,"=√") -> 7
A53: 40 | B53: 门店管理 | C53: 广告投放 | D53: 广告费报销 | E53: 是 | F53: 是 | G53: AE | H53: 是 | I53: 12036352 | J53: 额度内外业务合并 | K53: 广告费报销 | L53: 额度外广告费报销 | N53: 2 | O53: 权限导致功能报错，需排查 | R53: 除导出外不限 | S53: 编辑 | T53: √ | V53: √ | Y53: √ | AL53: √ | AM53: 编辑,导出 | AQ53: √ | AS53: 编辑 | AX53: √ | AY53: 导出 | AZ53: √ | BT53: =COUNTIF(T53:BS53,"=√") -> 7
A54: 41 | B54: 门店管理 | C54: 广告投放 | D54: 广告报销发票兑现 | E54: 是 | F54: 是 | G54: AE | H54: 是 | I54: 12036360 | J54: 额度内外业务合并 | K54: 广告报销兑现 | L54: 额度外广告报销兑现 | N54: 2 | O54: 1、3 | R54: 除导出外不限,打印 | S54: 编辑,打印 | T54: √ | V54: √ | Y54: √ | AL54: √ | AM54: 编辑,导出 | AQ54: √ | AS54: 编辑 | AX54: √ | AY54: 导出 | AZ54: √ | BR54: √ | BT54: =COUNTIF(T54:BS54,"=√") -> 8
A55: 42 | B55: 门店管理 | C55: 样品管理 | D55: 待定 | E55: 待定 | F55: 是，未来 | G55: AE/MBO | K55: 门店上样登记 | BT55: =COUNTIF(T55:BS55,"=√") -> 0
A56: 43 | B56: 门店管理 | C56: 样品管理 | D56: 待定 | E56: 待定 | F56: 是，未来 | G56: AE/MBO | K56: 门店样品处理 | BT56: =COUNTIF(T56:BS56,"=√") -> 0
A57: 44 | B57: 门店管理 | C57: 装修报表 | D57: 门店装修额外兑现报表（无） | F57: 是 | G57: AE | I57: 12036453 | K57: 门店装修额外兑现报表 | AL57: √ | AX57: √ | AY57: 导出 | BT57: =COUNTIF(T57:BS57,"=√") -> 2
A58: 46 | B58: 门店管理 | C58: 装修报表 | D58: 门店装修申请与进度更新报表 | F58: 是 | G58: AE | I58: 12036455 | K58: 门店装修申请与进度更新报表 | AL58: √ | AX58: √ | AY58: 导出 | BT58: =COUNTIF(T58:BS58,"=√") -> 2
A59: 47 | B59: 门店管理 | C59: 装修报表 | D59: 额度内兑现统计报表 | F59: 是 | G59: AE | I59: 12036456 | K59: 额度内兑现统计报表 | AX59: √ | AY59: 导出 | BT59: =COUNTIF(T59:BS59,"=√") -> 1
A60: 48 | B60: 门店管理 | C60: 装修报表 | D60: 店面额度内兑现余额表 | F60: 是 | G60: AE | I60: 12036488 | K60: 店面额度内兑现余额表 | AX60: √ | AY60: 导出 | BT60: =COUNTIF(T60:BS60,"=√") -> 1
A61: 49 | B61: 门店管理 | C61: 装修报表 | D61: 额度外台账（无） | F61: 是 | G61: AE | I61: 12036435 | K61: 额度外台账 | AL61: √ | AX61: √ | AY61: 导出 | BT61: =COUNTIF(T61:BS61,"=√") -> 2
A62: 50 | B62: 门店管理 | C62: 装修报表 | D62: 额度内台账（无） | F62: 是 | G62: AE | I62: 12036437 | K62: 额度内台账 | AL62: √ | AX62: √ | AY62: 导出 | BT62: =COUNTIF(T62:BS62,"=√") -> 2
A63: 51 | B63: 门店管理 | C63: 装修报表 | D63: 兑现汇总 | F63: 是 | G63: AE | I63: 12036436 | K63: 兑现汇总 | AL63: √ | AX63: √ | AY63: 导出 | BT63: =COUNTIF(T63:BS63,"=√") -> 2
A64: 52 | B64: 门店管理 | C64: 门店报表 | D64: 门店查询与分布（无） | F64: 是 | G64: AE | I64: 12036354 | K64: 门店查询与分布 | AL64: √ | AQ64: √ | AX64: √ | AY64: 导出 | BT64: =COUNTIF(T64:BS64,"=√") -> 3
A65: 53 | B65: 门店管理 | C65: 门店报表 | D65: 门店统计分析 | F65: 是 | G65: AE | I65: 12036338 | K65: 门店统计分析 | AL65: √ | AQ65: √ | AX65: √ | AY65: 导出 | BT65: =COUNTIF(T65:BS65,"=√") -> 3
A66: 54 | B66: 门店管理 | C66: 门店报表 | D66: 门店区域分布 | F66: 是 | G66: AE | I66: 12036401 | K66: 门店区域分布 | AL66: √ | AQ66: √ | AX66: √ | AY66: 导出 | BT66: =COUNTIF(T66:BS66,"=√") -> 3
A67: 55 | B67: 门店管理 | C67: 门店报表 | D67: 户外广告分布 | F67: 是 | G67: AE | I67: 12036341 | K67: 户外广告分布 | AL67: √ | AQ67: √ | AX67: √ | AY67: 导出 | BT67: =COUNTIF(T67:BS67,"=√") -> 3
A68: 56 | B68: 门店管理 | C68: 门店报表 | D68: 门店分析（无） | F68: 是 | G68: AE | I68: 12036365 | K68: 门店分析 | AL68: √ | AQ68: √ | AX68: √ | AY68: 导出 | BT68: =COUNTIF(T68:BS68,"=√") -> 3
A69: 57 | B69: 工程管理 | C69: 项目商机 | D69: 单体项目报备 | E69: 是 | F69: 是 | G69: AE | H69: 是 | I69: 12035833 | N69: 1 | O69: 1、3 | Q69: 1 | S69: 编辑,申诉 | T69: √ | Z69: √ | AG69: √,更新标准地址及信息,查重 | AI69: √,查重 | AZ69: √ | BT69: =COUNTIF(T69:BS69,"=√") -> 3
A70: 58 | B70: 工程管理 | C70: 项目商机 | D70: 项目进度更新 | E70: 是 | F70: 是 | G70: AE | H70: 是 | I70: 12035834 | N70: 4 | O70: 1、3 | Q70: 1 | S70: 编辑 | T70: √ | Z70: √ | AG70: √ | BT70: =COUNTIF(T70:BS70,"=√") -> 3
A71: 59 | B71: 工程管理 | C71: 项目商机 | D71: 战略项目报备 | F71: 是 | G71: AE | H71: 是 | I71: 12035908 | AG71: √ | AI71: √ | AN71: √ | AZ71: √ | BT71: =COUNTIF(T71:BS71,"=√") -> 4
A72: 60 | B72: 工程管理 | C72: 项目商机 | D72: 工程项目档案 | E72: 是 | F72: 是 | G72: AE | H72: 是 | I72: 12036099 | AG72: √ | AZ72: √ | BT72: =COUNTIF(T72:BS72,"=√") -> 2
A73: 61 | B73: 工程管理 | C73: 项目商机 | D73: 报备解冻申请 | E73: 是 | F73: 是 | G73: AE | H73: 是 | I73: 12036165 | N73: 3 | O73: 3 | Q73: 2 | R73: 除导出外不限 | S73: 编辑 | T73: √ | Z73: √ | AG73: √ | AZ73: √ | BT73: =COUNTIF(T73:BS73,"=√") -> 4
A74: 62 | B74: 工程管理 | C74: 项目商机 | D74: 报备生/失效申请 | F74: 是 | G74: AE | H74: 是 | I74: 12036168 | J74: 12036195 | K74: 单体项目报备失效申请 | L74: 单体项目报备生效申请 | Z74: √ | AG74: √ | AM74: 编辑 | AZ74: √ | BT74: =COUNTIF(T74:BS74,"=√") -> 3
A75: 63 | B75: 工程管理 | C75: 项目商机 | D75: 战略报备变更 | F75: 是 | G75: AE | H75: 是 | I75: 12036178 | AG75: √ | AN75: √ | BT75: =COUNTIF(T75:BS75,"=√") -> 2
A76: 64 | B76: 工程管理 | C76: 项目商机 | D76: 战略经理变更 | F76: 是 | G76: AE | H76: 是 | I76: 12036375 | R76: 导入 | AG76: √ | AM76: 编辑 | BT76: =COUNTIF(T76:BS76,"=√") -> 1
A77: 65 | B77: 工程管理 | C77: 项目商机 | D77: 工程项目结案 | E77: 是 | F77: 是 | G77: AE | H77: 是 | I77: 12035846 | N77: 4 | O77: X | Q77: 2 | S77: 编辑 | T77: √ | Z77: √ | AG77: √ | BT77: =COUNTIF(T77:BS77,"=√") -> 3
A78: 66 | B78: 工程管理 | C78: 项目合同 | D78: 经销商工程合同 | E78: 是 | F78: 是 | G78: AE | H78: 是 | I78: 12035844 | N78: 1 | O78: 1、3 | Q78: 1 | R78: 增补合同 | S78: 编辑 | T78: √ | Z78: √ | AJ78: √ | AM78: 失效,导出 | AN78: √ | AO78: √ | AU78: √ | AX78: √ | AY78: 导出 | AZ78: √ | BT78: =COUNTIF(T78:BS78,"=√") -> 8
A79: 67 | B79: 工程管理 | C79: 项目合同 | D79: 自营工程合同 | E79: 是 | F79: 是 | G79: AE | H79: 是 | I79: 12035907 | N79: 1 | O79: 1、3 | Q79: 1 | R79: 增补合同 | S79: 编辑 | T79: √ | AJ79: √ | AM79: 失效,导出 | AN79: √ | AO79: √ | AU79: √ | AX79: √ | AY79: 导出 | AZ79: √ | BT79: =COUNTIF(T79:BS79,"=√") -> 7
A80: 68 | B80: 工程管理 | C80: 项目交付 | D80: 工程合同产品变更 | E80: 是 | F80: 是 | G80: AE | H80: 是 | I80: 12036157 | N80: 1 | O80: 1、3 | Q80: 1 | R80: 删除 | S80: 编辑,删除 | T80: √ | Z80: √ | AJ80: √ | AM80: 导出 | AN80: √ | AO80: √ | AX80: √ | AY80: 导出 | BT80: =COUNTIF(T80:BS80,"=√") -> 6
A81: 69 | B81: 工程管理 | C81: 项目交付 | D81: 工程折扣延期 | E81: 是 | F81: 是 | G81: AE | H81: 是 | I81: 12036166 | N81: 1 | O81: 1、3 | Q81: 1 | R81: 删除 | S81: 编辑,删除 | T81: √ | Z81: √ | AJ81: √ | AM81: 导出 | AN81: √ | AO81: √ | AX81: √ | AY81: 导出 | BT81: =COUNTIF(T81:BS81,"=√") -> 6
A82: 70 | B82: 工程管理 | C82: 合同与折扣 | D82: 工程折扣单 | E82: 是 | F82: 是 | G82: AE | H82: 是 | I82: 12035849 | N82: 1 | O82: 3 | Q82: 2 | R82: 除导出外不限 | S82: 编辑 | T82: √ | Z82: √ | AJ82: √ | AM82: 导出 | AN82: √ | AO82: √ | AU82: √ | AX82: √ | AY82: 导出 | BT82: =COUNTIF(T82:BS82,"=√") -> 7
A83: 71 | B83: 工程管理 | C83: 合同与折扣 | D83: 项目合同变更 | E83: 是 | F83: 是 | G83: AE | H83: 是 | I83: 12035845 | R83: 除导出外不限 | AJ83: √ | AX83: √ | AY83: 导出 | BT83: =COUNTIF(T83:BS83,"=√") -> 2
A84: 72 | B84: 工程管理 | C84: 项目交付 | D84: 工程折扣政策申请 | F84: 是 | G84: AE | H84: 是 | I84: 12036490 | R84: 除导出外不限 | AL84: √ | AM84: 编辑 | AO84: √ | AT84: √ | AX84: √ | AY84: 导出 | BT84: =COUNTIF(T84:BS84,"=√") -> 4
A85: 73 | B85: 工程管理 | C85: 项目交付 | D85: 工程折扣政策失效 | F85: 是 | G85: AE | H85: 是 | I85: 12036491 | R85: 除导出外不限 | AL85: √ | AM85: 编辑 | AX85: √ | BT85: =COUNTIF(T85:BS85,"=√") -> 2
A86: 74 | B86: 工程管理 | C86: 项目交付 | D86: 工程要货订单 | E86: 是 | F86: 是 | G86: AE | H86: 是 | I86: 12035851 | N86: 1 | O86: 1、3 | Q86: 1 | R86: 同步地址信息,查看定金与库存,申请不扣定金,打印 | S86: 编辑,修改地址 | T86: √ | W86: √ | Y86: √ | AC86: √ | AJ86: √ | AM86: 导出 | AN86: √ | AO86: √ | AT86: √ | AV86: √ | AX86: √ | AY86: 导出 | BT86: =COUNTIF(T86:BS86,"=√") -> 10
A87: 75 | B87: 工程管理 | C87: 合同与折扣 | D87: 工程自营签收 | E87: 是 | F87: 是 | G87: AE | H87: 是 | I87: 12035854 | N87: 1 | O87: 1、3 | Q87: 2 | S87: 编辑 | T87: √ | Y87: √ | AJ87: √ | AN87: √ | AO87: √ | AS87: 导出 | AX87: √ | AY87: 导出 | BA87: √ | BT87: =COUNTIF(T87:BS87,"=√") -> 7
A88: 76 | B88: 工程管理 | C88: 项目交付 | D88: 订单紧急要货 | E88: 是 | F88: 是 | G88: AE | H88: 是 | I88: 12036177 | N88: 5 | Q88: 功能权限有问题，先去掉权限 | R88: 除导出外不限 | S88: 编辑 | T88: √ | W88: √ | Y88: √ | AJ88: √ | AO88: √ | AT88: √ | AV88: √ | AX88: √ | AY88: 导出 | BT88: =COUNTIF(T88:BS88,"=√") -> 8
A89: 77 | B89: 工程管理 | C89: 项目交付 | D89: 提货时间变更 | F89: 是 | G89: AE | H89: 是 | I89: 12036189 | Y89: √ | AT89: √ | AV89: √ | AW89: 编辑 | AX89: √ | AY89: 导出 | BT89: =COUNTIF(T89:BS89,"=√") -> 4
A90: 78 | B90: 工程管理 | C90: 项目交付 | D90: 有效延期申请 | E90: 是 | F90: 是 | G90: AE | H90: 是 | I90: 12036190 | N90: 6 | R90: 除导出外不限 | S90: 编辑 | T90: √ | W90: √ | Y90: √ | AO90: √ | AT90: √ | AV90: √ | AW90: 编辑 | AX90: √ | AY90: 导出 | BT90: =COUNTIF(T90:BS90,"=√") -> 7
A91: 79 | B91: 工程管理 | C91: 项目交付 | D91: 紧急要货插单 | F91: 是 | G91: AE | H91: 是 | I91: 12036191 | R91: 除导出外不限 | Y91: √ | AT91: √ | AV91: √ | AW91: 编辑 | AX91: √ | AY91: 导出 | BT91: =COUNTIF(T91:BS91,"=√") -> 4
A92: 80 | B92: 工程管理 | C92: 项目交付 | D92: 工程要货订单报表 | E92: 是 | F92: 是 | G92: AE | I92: 12036171 | N92: 4 | R92: 除导出外不限 | T92: √ | Y92: √ | AJ92: √ | AN92: √ | AO92: √ | AX92: √ | AY92: 导出 | BT92: =COUNTIF(T92:BS92,"=√") -> 6
A93: 81 | B93: 工程管理 | C93: 项目交付 | D93: 折扣单报表 | E93: 是 | F93: 是 | G93: AE | I93: 12036173 | N93: 4 | R93: 除导出外不限 | T93: √ | Y93: √ | AJ93: √ | AN93: √ | AO93: √ | AX93: √ | AY93: 导出 | BT93: =COUNTIF(T93:BS93,"=√") -> 6
A94: 82 | B94: 工程管理 | C94: 项目交付 | D94: 紧急要货报表 | E94: 是 | F94: 是 | G94: AE | I94: 12036196 | R94: 除导出外不限 | AT94: √ | AV94: √ | AX94: √ | AY94: 导出 | BT94: =COUNTIF(T94:BS94,"=√") -> 3
A95: 83 | B95: 工程管理 | C95: 项目交付 | D95: 提货时间变更表 | F95: 是 | G95: AE | I95: 12036197 | R95: 除导出外不限 | AT95: √ | AV95: √ | AX95: √ | AY95: 导出 | BT95: =COUNTIF(T95:BS95,"=√") -> 3
A96: 84 | B96: 工程管理 | C96: 项目交付 | D96: 插单记录表 | F96: 是 | G96: AE | I96: 12036198 | R96: 除导出外不限 | AT96: √ | AV96: √ | AX96: √ | AY96: 导出 | BT96: =COUNTIF(T96:BS96,"=√") -> 3
A97: 85 | B97: 工程管理 | C97: 服务费 | D97: 工程服务费报销 | E97: 是 | F97: 是 | G97: AE | H97: 是 | I97: 12036461 | N97: 2 | O97: 1、3 | R97: 除导出外不限 | S97: 编辑 | T97: √ | Y97: √ | AG97: √ | AJ97: √ | AX97: √ | AY97: 导出 | BT97: =COUNTIF(T97:BS97,"=√") -> 5
A98: 86 | B98: 工程管理 | C98: 服务费 | D98: 工程服务费兑现 | E98: 是 | F98: 是 | G98: AE | H98: 是 | I98: 12036462 | N98: 1 | O98: 1、3 | R98: 除导出外不限 | S98: 编辑 | T98: √ | Y98: √ | AG98: √ | AJ98: √ | AX98: √ | AY98: 导出 | BT98: =COUNTIF(T98:BS98,"=√") -> 5
A99: 87 | B99: 工程管理 | C99: 项目往来 | D99: 项目到款引入 | F99: 是 | G99: AE | H99: 是 | I99: 12035864 | N99: 1 | O99: 1、3 | R99: 除导出外不限 | S99: 编辑 | T99: √ | Y99: √ | AG99: √ | AJ99: √ | AM99: 编辑 | AN99: √ | AO99: √ | AX99: √ | AY99: 导出,确认兑付 | BT99: =COUNTIF(T99:BS99,"=√") -> 7
A100: 88 | B100: 工程管理 | C100: 项目往来 | D100: 项目到款认领 | F100: 是 | G100: AE | H100: 是 | I100: 12035865 | N100: 1 | O100: 1、3 | R100: 除导出外不限 | S100: 编辑 | T100: √ | Y100: √ | AG100: √ | AJ100: √ | AM100: 编辑 | AN100: √ | AO100: √ | AX100: √ | AY100: 导出 | BT100: =COUNTIF(T100:BS100,"=√") -> 7
...

Sheet MBO计划菜单
A1: 序号 | B1: 客户端 | C1: 模块 | D1: 一级菜单 | E1: 二级菜单 | F1: 三级菜单 | G1: 四级菜单 | H1: 合并 | I1: 备注 | J1: 业务确认
A2: 1 | B2: 经销商侧PC端 | C2: 到岸价 | D2: 采购管理 | E2: 经销商采购 | F2: 行程轨迹管理 | G2: 采购订单发运列表 | J2: 常规业务，正常使用
B3: 经销商侧PC端 | C3: 到岸价 | D3: 采购管理 | E3: 经销商采购 | F3: 行程轨迹管理 | G3: 出库单发运列表
A4: 2 | B4: 经销商侧PC端 | C4: 到岸价 | D4: 采购管理 | E4: 经销商采购 | F4: 异常反馈管理 | G4: 异常反馈列表
B5: 经销商侧PC端 | C5: 到岸价 | D5: 采购管理 | E5: 经销商采购 | F5: 异常反馈管理 | G5: 异常查询列表
A6: 3 | B6: 经销商侧PC端 | C6: 到岸价 | D6: 采购管理 | E6: 经销商采购 | F6: 待发运管理 | G6: 出库单确认列表
A7: 4 | B7: 经销商侧PC端 | C7: 到岸价 | D7: 采购管理 | E7: 经销商采购 | F7: 待确认收货 | G7: 待确认发货列表
A8: 5 | B8: 经销商侧PC端 | C8: 到岸价 | D8: 采购管理 | E8: 经销商采购 | F8: 异常费用 | G8: 异常费用
A9: 6 | B9: 品牌侧PC端 | C9: 到岸价 | D9: 采购管理 | E9: 经销商采购 | F9: 行程轨迹管理
A10: 7 | B10: 品牌侧PC端 | C10: 到岸价 | D10: 采购管理 | E10: 经销商采购 | F10: 异常反馈管理
A11: 8 | B11: 品牌侧PC端 | C11: 到岸价 | D11: 采购管理 | E11: 经销商采购 | F11: 确认发货配置项 | G11: 确认发货配置项列表
A12: 9 | B12: 品牌侧PC端 | C12: 电子合同 | D12: 经销商 | E12: 合同管理 | F12: 模板管理 | G12: 模版管理 | J12: 常规业务，正常使用
A13: 10 | B13: 品牌侧PC端 | C13: 电子合同 | D13: 经销商 | E13: 合同管理 | F13: 合同管理 | G13: 经销合同管理 | I13: 经销合同、装修协议、广告协议、授权书、联络函、点将合同
A14: 11 | B14: 品牌侧PC端 | C14: 电子合同 | D14: 经销商 | E14: 合同管理 | F14: 合同管理 | G14: 装修协议
A15: 12 | B15: 品牌侧PC端 | C15: 电子合同 | D15: 经销商 | E15: 合同管理 | F15: 合同管理 | G15: 广告协议
A16: 13 | B16: 品牌侧PC端 | C16: 电子合同 | D16: 经销商 | E16: 合同管理 | F16: 合同管理 | G16: 授权书管理 | I16: 导购营销助手APP，使用品牌侧账号登录 | J16: 反馈：已于25年初停用，不迁移 确认人：袁娱
B17: 品牌侧PC端 | C17: 电子合同 | D17: 经销商 | E17: 合同管理 | F17: 合同管理 | G17: 联络函管理
B18: 品牌侧PC端 | C18: 电子合同 | D18: 经销商 | E18: 合同管理 | F18: 合同管理 | G18: 点将合同(1.5)
B19: 品牌侧PC端 | C19: 电子合同 | D19: 经销商 | E19: 合同管理 | F19: 合同处理 | G19: 经销商拒签待处理
B20: 经销商侧PC端 | C20: 电子合同 | D20: 基础 | E20: 合同管理 | F20: 合同 | G20: 经销商合同
B21: 经销商侧PC端 | C21: 电子合同 | D21: 基础 | E21: 合同管理 | F21: 合同 | G21: 装修协议
B22: 经销商侧PC端 | C22: 电子合同 | D22: 基础 | E22: 合同管理 | F22: 合同 | G22: 广告协议
B23: 经销商侧PC端 | C23: 电子合同 | D23: 基础 | E23: 合同管理 | F23: 合同 | G23: 点将合同
B24: 经销商侧PC端 | C24: 电子合同 | D24: 基础 | E24: 合同管理 | F24: 合同 | G24: *所有合同
A25: 15 | B25: 品牌侧PC端 | C25: 分销订货会 | D25: 营销 | E25: 分销订货会 | F25: 分销商订货计划 | J25: 反馈：目前已没有使用，可以往后安排 确认人：林文宇
A26: 16 | B26: 品牌侧PC端 | C26: 分销订货会 | D26: 营销 | E26: 分销订货会 | F26: 分销商订货列表
A27: 17 | B27: 品牌侧PC端 | C27: 分销订货会 | D27: 营销 | E27: 分销订货会 | F27: 分销订货会审核
A28: 18 | B28: 品牌侧PC端 | C28: 分销订货会 | D28: 营销 | E28: 分销订货会 | F28: 分销订货会统计
A29: 19 | B29: 经销商侧PC端 | C29: 分销订货会 | D29: 营销 | E29: 分销订货会 | F29: 分销商订货计划
A30: 20 | B30: 经销商侧PC端 | C30: 分销订货会 | D30: 营销 | E30: 分销订货会 | F30: 分销商订货列表
A31: 21 | B31: 品牌侧PC端 | C31: 心声社区 | D31: 心声社区 | J31: 反馈：市场反馈由审计及营销管理部在使用（原对外入口由于数据安全问题已关闭），售后对接客服系统，均在正常使用 确认人：林文宇
A32: 22 | B32: 经销商侧PC端 | C32: 心声社区 | D32: 心声社区
A33: 28 | B33: 品牌侧PC端 | C33: 点将 | D33: 营销 | E33: 点将 | F33: 基础信息 | G33: 讲师档案 | J33: 常规业务，正常使用
B34: 品牌侧PC端 | C34: 点将 | D34: 营销 | E34: 点将 | F34: 基础信息 | G34: 讲师排期
B35: 品牌侧PC端 | C35: 点将 | D35: 营销 | E35: 点将 | F35: 基础信息 | G35: 策划师档案
B36: 品牌侧PC端 | C36: 点将 | D36: 营销 | E36: 点将 | F36: 基础信息 | G36: 培训师档案
B37: 品牌侧PC端 | C37: 点将 | D37: 营销 | E37: 点将 | F37: 基础信息 | G37: 设计师档案
B38: 品牌侧PC端 | C38: 点将 | D38: 营销 | E38: 点将 | F38: 基础信息 | G38: 策划师档案审批
B39: 品牌侧PC端 | C39: 点将 | D39: 营销 | E39: 点将 | F39: 基础信息 | G39: 培训师档案审批
B40: 品牌侧PC端 | C40: 点将 | D40: 营销 | E40: 点将 | F40: 基础信息 | G40: 设计师档案审批
B41: 品牌侧PC端 | C41: 点将 | D41: 营销 | E41: 点将 | F41: 基础信息 | G41: 设计师饱和度
B42: 品牌侧PC端 | C42: 点将 | D42: 营销 | E42: 点将 | F42: 基础信息 | G42: 特训营管理
B43: 品牌侧PC端 | C43: 点将 | D43: 营销 | E43: 点将 | F43: 基础信息 | G43: 评价模版列表
A44: 29 | B44: 品牌侧PC端 | C44: 点将 | D44: 营销 | E44: 点将 | F44: 点将管理 | G44: 活动点将管理
B45: 品牌侧PC端 | C45: 点将 | D45: 营销 | E45: 点将 | F45: 点将管理 | G45: 特训营点将管理
B46: 品牌侧PC端 | C46: 点将 | D46: 营销 | E46: 点将 | F46: 点将管理 | G46: 设计点将管理
B47: 品牌侧PC端 | C47: 点将 | D47: 营销 | E47: 点将 | F47: 点将管理 | G47: 活动点将审批
B48: 品牌侧PC端 | C48: 点将 | D48: 营销 | E48: 点将 | F48: 点将管理 | G48: 活动取消审批(无数据)
B49: 品牌侧PC端 | C49: 点将 | D49: 营销 | E49: 点将 | F49: 点将管理 | G49: 特训营点将审批
B50: 品牌侧PC端 | C50: 点将 | D50: 营销 | E50: 点将 | F50: 点将管理 | G50: 特训营取消审批(2，无数据)
B51: 品牌侧PC端 | C51: 点将 | D51: 营销 | E51: 点将 | F51: 点将管理 | G51: 设计点将审批
B52: 品牌侧PC端 | C52: 点将 | D52: 营销 | E52: 点将 | F52: 点将管理 | G52: 点将活动(策)
B53: 品牌侧PC端 | C53: 点将 | D53: 营销 | E53: 点将 | F53: 点将管理 | G53: 点将活动(单)
B54: 品牌侧PC端 | C54: 点将 | D54: 营销 | E54: 点将 | F54: 点将管理 | G54: 点将活动(设)(4）
B55: 品牌侧PC端 | C55: 点将 | D55: 营销 | E55: 点将 | F55: 点将管理 | G55: 特训营(培)(无数据)
B56: 品牌侧PC端 | C56: 点将 | D56: 营销 | E56: 点将 | F56: 点将管理 | G56: 单店点将培训审批(无数据)
B57: 品牌侧PC端 | C57: 点将 | D57: 营销 | E57: 点将 | F57: 点将管理 | G57: 设计点将审批（设）(无数据）
A58: 30 | B58: 品牌侧PC端 | C58: 点将 | D58: 营销 | E58: 点将 | F58: 点将管理 | G58: 设计点将取消审批(无数据)
A59: 31 | B59: 品牌侧PC端 | C59: 点将 | D59: 营销 | E59: 点将 | F59: 点将管理 | G59: 点将活动(特)(无数据)
A60: 32 | B60: 品牌侧PC端 | C60: 点将 | D60: 营销 | E60: 点将 | F60: 点将管理 | G60: 设计点将取消审批(设计师)(无数据)
A61: 33 | B61: 品牌侧PC端 | C61: 点将 | D61: 营销 | E61: 点将 | F61: 点将管理 | G61: 单店培训点将管理
A62: 30 | B62: 经销商侧PC端 | C62: 点将 | D62: 事务管理 | E62: 点将管理 | F62: 点将管理 | G62: 活动
A63: 31 | B63: 经销商侧PC端 | C63: 点将 | D63: 事务管理 | E63: 点将管理 | F63: 点将管理 | G63: 设计
A64: 32 | B64: 经销商侧PC端 | C64: 点将 | D64: 事务管理 | E64: 点将管理 | F64: 点将管理 | G64: 特训营
A65: 33 | B65: 经销商侧PC端 | C65: 点将 | D65: 事务管理 | E65: 点将管理 | F65: 点将管理 | G65: 单店
A66: 36 | B66: 品牌侧PC端 | C66: 上下样管理 | D66: 出样管理 | E66: 出样计划管理 | F66: 出样计划列表 | J66: 反馈：仍在继续使用，只是未进行强制考核，且有调整需求 确认人：林文宇
A67: 37 | B67: 品牌侧PC端 | C67: 上下样管理 | D67: 出样管理 | E67: 出样计划管理 | F67: 出样计划审批
A68: 38 | B68: 品牌侧PC端 | C68: 上下样管理 | D68: 出样管理 | E68: 出样计划管理 | F68: 出样计划下发
A69: 39 | B69: 品牌侧PC端 | C69: 上下样管理 | D69: 出样管理 | E69: 出样计划管理 | F69: 产品出样考核标准
A70: 40 | B70: 品牌侧PC端 | C70: 上下样管理 | D70: 出样管理 | E70: 出样计划管理 | F70: 样品展示图片
A71: 41 | B71: 品牌侧PC端 | C71: 上下样管理 | D71: 出样管理 | E71: 出样计划管理 | F71: 样品台账
A72: 42 | B72: 品牌侧PC端 | C72: 上下样管理 | D72: 出样管理 | E72: 出样计划管理 | F72: 样品明细
A73: 43 | B73: 经销商侧PC端 | C73: 上下样管理 | D73: 出样管理 | E73: 出样管理 | F73: 出样计划查询
A74: 44 | B74: 经销商侧PC端 | C74: 上下样管理 | D74: 出样管理 | E74: 出样管理 | F74: 上下样单查询
A75: 45 | B75: 经销商侧PC端 | C75: 上下样管理 | D75: 出样管理 | E75: 出样管理 | F75: 样品展示图片
A76: 46 | B76: 经销商侧PC端 | C76: 上下样管理 | D76: 出样管理 | E76: 出样管理 | F76: 样品台账
A77: 47 | B77: 经销商侧PC端 | C77: 上下样管理 | D77: 出样管理 | E77: 出样管理 | F77: 样品明细
